<?xml version="1.0" encoding="ISO-8859-1"?><EQUIPMENTS>
<EQUIPMENT>
 <NAME>All Grain - Large 10 Gal/38 l - Cooler</NAME>
 <VERSION>1</VERSION>
 <BOIL_SIZE>47.6520253</BOIL_SIZE>
 <BATCH_SIZE>37.8541178</BATCH_SIZE>
 <TUN_VOLUME>37.8541178</TUN_VOLUME>
 <TUN_WEIGHT>4.0823280</TUN_WEIGHT>
 <TUN_SPECIFIC_HEAT>0.3000000</TUN_SPECIFIC_HEAT>
 <TOP_UP_WATER>0.0000000</TOP_UP_WATER>
 <TRUB_CHILLER_LOSS>3.7854118</TRUB_CHILLER_LOSS>
 <EVAP_RATE>8.9765656</EVAP_RATE>
 <BOIL_TIME>60.0000000</BOIL_TIME>
 <CALC_BOIL_VOLUME>TRUE</CALC_BOIL_VOLUME>
 <LAUTER_DEADSPACE>3.0283294</LAUTER_DEADSPACE>
 <TOP_UP_KETTLE>0.0000000</TOP_UP_KETTLE>
 <HOP_UTILIZATION>100.0000000</HOP_UTILIZATION>
 <COOLING_LOSS_PCT>4.0000000</COOLING_LOSS_PCT>
 <NOTES>Popular 10 gallon/38 liter setup for all grain brewing.  Uses a 10 gal/38 l water cooler as mash tun for single infusion mashes and a 15 gallon brew pot for full size boil of the 12+ gallons of wort.</NOTES>
 <DISPLAY_BOIL_SIZE>47.65 L</DISPLAY_BOIL_SIZE>
 <DISPLAY_BATCH_SIZE>37.85 L</DISPLAY_BATCH_SIZE>
 <DISPLAY_TUN_VOLUME>37.85 L</DISPLAY_TUN_VOLUME>
 <DISPLAY_TUN_WEIGHT>4.08 kg</DISPLAY_TUN_WEIGHT>
 <DISPLAY_TOP_UP_WATER>0.00 L</DISPLAY_TOP_UP_WATER>
 <DISPLAY_TRUB_CHILLER_LOSS>3.79 L</DISPLAY_TRUB_CHILLER_LOSS>
 <DISPLAY_LAUTER_DEADSPACE>3.03 L</DISPLAY_LAUTER_DEADSPACE>
 <DISPLAY_TOP_UP_KETTLE>0.00 L</DISPLAY_TOP_UP_KETTLE>
</EQUIPMENT>
<EQUIPMENT>
 <NAME>All Grain - Large 10 Gal/38 l - Stainless</NAME>
 <VERSION>1</VERSION>
 <BOIL_SIZE>50.9453336</BOIL_SIZE>
 <BATCH_SIZE>37.8541178</BATCH_SIZE>
 <TUN_VOLUME>56.7811768</TUN_VOLUME>
 <TUN_WEIGHT>9.0718400</TUN_WEIGHT>
 <TUN_SPECIFIC_HEAT>0.1500000</TUN_SPECIFIC_HEAT>
 <TOP_UP_WATER>0.0000000</TOP_UP_WATER>
 <TRUB_CHILLER_LOSS>3.7854118</TRUB_CHILLER_LOSS>
 <EVAP_RATE>14.8606811</EVAP_RATE>
 <BOIL_TIME>60.0000000</BOIL_TIME>
 <CALC_BOIL_VOLUME>TRUE</CALC_BOIL_VOLUME>
 <LAUTER_DEADSPACE>3.7854118</LAUTER_DEADSPACE>
 <TOP_UP_KETTLE>0.0000000</TOP_UP_KETTLE>
 <HOP_UTILIZATION>100.0000000</HOP_UTILIZATION>
 <COOLING_LOSS_PCT>4.0000000</COOLING_LOSS_PCT>
 <NOTES>Popular 10 gal/38 l batch setup for all grain brewing.  Uses two large stainless 15 gal/58 l kegs or pots for the boil pot and mash tun with the tops cut off the keg.  A third keg or large pot is often used as a pot to heat mash tun water.</NOTES>
 <DISPLAY_BOIL_SIZE>50.95 L</DISPLAY_BOIL_SIZE>
 <DISPLAY_BATCH_SIZE>37.85 L</DISPLAY_BATCH_SIZE>
 <DISPLAY_TUN_VOLUME>56.78 L</DISPLAY_TUN_VOLUME>
 <DISPLAY_TUN_WEIGHT>9.07 kg</DISPLAY_TUN_WEIGHT>
 <DISPLAY_TOP_UP_WATER>0.00 L</DISPLAY_TOP_UP_WATER>
 <DISPLAY_TRUB_CHILLER_LOSS>3.79 L</DISPLAY_TRUB_CHILLER_LOSS>
 <DISPLAY_LAUTER_DEADSPACE>3.79 L</DISPLAY_LAUTER_DEADSPACE>
 <DISPLAY_TOP_UP_KETTLE>0.00 L</DISPLAY_TOP_UP_KETTLE>
</EQUIPMENT>
<EQUIPMENT>
 <NAME>All Grain - Mini 3 Gal/11.3 l - BIAB Stovetop</NAME>
 <VERSION>1</VERSION>
 <BOIL_SIZE>13.9508197</BOIL_SIZE>
 <BATCH_SIZE>11.3562354</BATCH_SIZE>
 <TUN_VOLUME>22.7124707</TUN_VOLUME>
 <TUN_WEIGHT>2.2679600</TUN_WEIGHT>
 <TUN_SPECIFIC_HEAT>0.1200000</TUN_SPECIFIC_HEAT>
 <TOP_UP_WATER>0.0000000</TOP_UP_WATER>
 <TRUB_CHILLER_LOSS>0.9463529</TRUB_CHILLER_LOSS>
 <EVAP_RATE>8.1401922</EVAP_RATE>
 <BOIL_TIME>60.0000000</BOIL_TIME>
 <CALC_BOIL_VOLUME>TRUE</CALC_BOIL_VOLUME>
 <LAUTER_DEADSPACE>0.0000000</LAUTER_DEADSPACE>
 <TOP_UP_KETTLE>0.0000000</TOP_UP_KETTLE>
 <HOP_UTILIZATION>100.0000000</HOP_UTILIZATION>
 <COOLING_LOSS_PCT>4.0000000</COOLING_LOSS_PCT>
 <NOTES>Mini Brew-in-a-bag stovetop all grain batch with a  a 3 gal/11l target batch volume designed to fit in a 5-6 gal pot.  Note that pot size dictates how much grain can be used and you may need more than 5 gal/19 l for higher gravity beers.  Please use a BIAB mash profile with this setup to get the proper mash volumes.</NOTES>
 <DISPLAY_BOIL_SIZE>13.95 L</DISPLAY_BOIL_SIZE>
 <DISPLAY_BATCH_SIZE>11.36 L</DISPLAY_BATCH_SIZE>
 <DISPLAY_TUN_VOLUME>22.71 L</DISPLAY_TUN_VOLUME>
 <DISPLAY_TUN_WEIGHT>2.27 kg</DISPLAY_TUN_WEIGHT>
 <DISPLAY_TOP_UP_WATER>0.00 L</DISPLAY_TOP_UP_WATER>
 <DISPLAY_TRUB_CHILLER_LOSS>0.95 L</DISPLAY_TRUB_CHILLER_LOSS>
 <DISPLAY_LAUTER_DEADSPACE>0.00 L</DISPLAY_LAUTER_DEADSPACE>
 <DISPLAY_TOP_UP_KETTLE>0.00 L</DISPLAY_TOP_UP_KETTLE>
</EQUIPMENT>
<EQUIPMENT>
 <NAME>All Grain - Standard 5 Gal/19l Batch - Cooler</NAME>
 <VERSION>1</VERSION>
 <BOIL_SIZE>24.7171617</BOIL_SIZE>
 <BATCH_SIZE>18.9270589</BATCH_SIZE>
 <TUN_VOLUME>18.9270589</TUN_VOLUME>
 <TUN_WEIGHT>1.8143680</TUN_WEIGHT>
 <TUN_SPECIFIC_HEAT>0.3000000</TUN_SPECIFIC_HEAT>
 <TOP_UP_WATER>0.0000000</TOP_UP_WATER>
 <TRUB_CHILLER_LOSS>2.8390588</TRUB_CHILLER_LOSS>
 <EVAP_RATE>8.2700530</EVAP_RATE>
 <BOIL_TIME>60.0000000</BOIL_TIME>
 <CALC_BOIL_VOLUME>TRUE</CALC_BOIL_VOLUME>
 <LAUTER_DEADSPACE>0.9463529</LAUTER_DEADSPACE>
 <TOP_UP_KETTLE>0.0000000</TOP_UP_KETTLE>
 <HOP_UTILIZATION>100.0000000</HOP_UTILIZATION>
 <COOLING_LOSS_PCT>4.0000000</COOLING_LOSS_PCT>
 <NOTES>Popular all grain setup.  5 Gal/19 l Plastic cooler as mash tun with false bottom, and 7-9 gallon brewpot capable of boiling at least 7 gal of wort without spilling over.  Primarily used for single infusion mashes.</NOTES>
 <DISPLAY_BOIL_SIZE>24.72 L</DISPLAY_BOIL_SIZE>
 <DISPLAY_BATCH_SIZE>18.93 L</DISPLAY_BATCH_SIZE>
 <DISPLAY_TUN_VOLUME>18.93 L</DISPLAY_TUN_VOLUME>
 <DISPLAY_TUN_WEIGHT>1.81 kg</DISPLAY_TUN_WEIGHT>
 <DISPLAY_TOP_UP_WATER>0.00 L</DISPLAY_TOP_UP_WATER>
 <DISPLAY_TRUB_CHILLER_LOSS>2.84 L</DISPLAY_TRUB_CHILLER_LOSS>
 <DISPLAY_LAUTER_DEADSPACE>0.95 L</DISPLAY_LAUTER_DEADSPACE>
 <DISPLAY_TOP_UP_KETTLE>0.00 L</DISPLAY_TOP_UP_KETTLE>
</EQUIPMENT>
<EQUIPMENT>
 <NAME>All Grain - Standard 5 Gal/19l Batch - Stainless</NAME>
 <VERSION>1</VERSION>
 <BOIL_SIZE>24.7171617</BOIL_SIZE>
 <BATCH_SIZE>18.9270589</BATCH_SIZE>
 <TUN_VOLUME>18.9270589</TUN_VOLUME>
 <TUN_WEIGHT>3.6287360</TUN_WEIGHT>
 <TUN_SPECIFIC_HEAT>0.1200000</TUN_SPECIFIC_HEAT>
 <TOP_UP_WATER>0.0000000</TOP_UP_WATER>
 <TRUB_CHILLER_LOSS>2.8390588</TRUB_CHILLER_LOSS>
 <EVAP_RATE>8.2700530</EVAP_RATE>
 <BOIL_TIME>60.0000000</BOIL_TIME>
 <CALC_BOIL_VOLUME>TRUE</CALC_BOIL_VOLUME>
 <LAUTER_DEADSPACE>0.9463529</LAUTER_DEADSPACE>
 <TOP_UP_KETTLE>0.0000000</TOP_UP_KETTLE>
 <HOP_UTILIZATION>100.0000000</HOP_UTILIZATION>
 <COOLING_LOSS_PCT>4.0000000</COOLING_LOSS_PCT>
 <NOTES>Popular all grain setup.  5 Gal/19 l stainless pot as mash tun with false bottom, and 7-9 gallon brewpot capable of boiling at least 7 gal of wort without spilling over.  Primarily used for single infusion mashes.</NOTES>
 <DISPLAY_BOIL_SIZE>24.72 L</DISPLAY_BOIL_SIZE>
 <DISPLAY_BATCH_SIZE>18.93 L</DISPLAY_BATCH_SIZE>
 <DISPLAY_TUN_VOLUME>18.93 L</DISPLAY_TUN_VOLUME>
 <DISPLAY_TUN_WEIGHT>3.63 kg</DISPLAY_TUN_WEIGHT>
 <DISPLAY_TOP_UP_WATER>0.00 L</DISPLAY_TOP_UP_WATER>
 <DISPLAY_TRUB_CHILLER_LOSS>2.84 L</DISPLAY_TRUB_CHILLER_LOSS>
 <DISPLAY_LAUTER_DEADSPACE>0.95 L</DISPLAY_LAUTER_DEADSPACE>
 <DISPLAY_TOP_UP_KETTLE>0.00 L</DISPLAY_TOP_UP_KETTLE>
</EQUIPMENT>
<EQUIPMENT>
 <NAME>BIAB - Large 10 Gal/38 l Batch</NAME>
 <VERSION>1</VERSION>
 <BOIL_SIZE>55.5666905</BOIL_SIZE>
 <BATCH_SIZE>37.8541178</BATCH_SIZE>
 <TUN_VOLUME>75.7082357</TUN_VOLUME>
 <TUN_WEIGHT>10.8862080</TUN_WEIGHT>
 <TUN_SPECIFIC_HEAT>0.1200000</TUN_SPECIFIC_HEAT>
 <TOP_UP_WATER>0.0000000</TOP_UP_WATER>
 <TRUB_CHILLER_LOSS>5.6781177</TRUB_CHILLER_LOSS>
 <EVAP_RATE>12.2622765</EVAP_RATE>
 <BOIL_TIME>90.0000000</BOIL_TIME>
 <CALC_BOIL_VOLUME>TRUE</CALC_BOIL_VOLUME>
 <LAUTER_DEADSPACE>0.0000000</LAUTER_DEADSPACE>
 <TOP_UP_KETTLE>0.0000000</TOP_UP_KETTLE>
 <HOP_UTILIZATION>100.0000000</HOP_UTILIZATION>
 <COOLING_LOSS_PCT>4.0000000</COOLING_LOSS_PCT>
 <NOTES>Sample Brew-in-a-bag equipment profile set up for a 20 Gal/70 liter brewing pot  (diameter of 45cm or 18 inches) and using a polyester grain bag to hold the grain.  This profile should be used with the BIAB mash profiles available in the BeerSmith mash profiles area. The above assumes loose pellet hops and only clear, chilled wort transferred from the kettle using no trub management techniques. Experienced brewers should adjust &#39;Loss to Trub and Chiller&#39; and &#39;Brewhouse Efficiency&#39; accordingly to suit their trub management techniques. Careful when mashing in as this profile approaches the pot limits.</NOTES>
 <DISPLAY_BOIL_SIZE>55.57 L</DISPLAY_BOIL_SIZE>
 <DISPLAY_BATCH_SIZE>37.85 L</DISPLAY_BATCH_SIZE>
 <DISPLAY_TUN_VOLUME>75.71 L</DISPLAY_TUN_VOLUME>
 <DISPLAY_TUN_WEIGHT>10.89 kg</DISPLAY_TUN_WEIGHT>
 <DISPLAY_TOP_UP_WATER>0.00 L</DISPLAY_TOP_UP_WATER>
 <DISPLAY_TRUB_CHILLER_LOSS>5.68 L</DISPLAY_TRUB_CHILLER_LOSS>
 <DISPLAY_LAUTER_DEADSPACE>0.00 L</DISPLAY_LAUTER_DEADSPACE>
 <DISPLAY_TOP_UP_KETTLE>0.00 L</DISPLAY_TOP_UP_KETTLE>
</EQUIPMENT>
<EQUIPMENT>
 <NAME>BIAB - Standard 5 Gal/19 l Batch</NAME>
 <VERSION>1</VERSION>
 <BOIL_SIZE>30.7359664</BOIL_SIZE>
 <BATCH_SIZE>18.9270589</BATCH_SIZE>
 <TUN_VOLUME>56.7811768</TUN_VOLUME>
 <TUN_WEIGHT>6.8038800</TUN_WEIGHT>
 <TUN_SPECIFIC_HEAT>0.1200000</TUN_SPECIFIC_HEAT>
 <TOP_UP_WATER>0.0000000</TOP_UP_WATER>
 <TRUB_CHILLER_LOSS>2.8390588</TRUB_CHILLER_LOSS>
 <EVAP_RATE>17.4885821</EVAP_RATE>
 <BOIL_TIME>90.0000000</BOIL_TIME>
 <CALC_BOIL_VOLUME>TRUE</CALC_BOIL_VOLUME>
 <LAUTER_DEADSPACE>0.0000000</LAUTER_DEADSPACE>
 <TOP_UP_KETTLE>0.0000000</TOP_UP_KETTLE>
 <HOP_UTILIZATION>100.0000000</HOP_UTILIZATION>
 <COOLING_LOSS_PCT>4.0000000</COOLING_LOSS_PCT>
 <NOTES>Sample Brew-In-A-Bag equipment profile set up for a 15 Gal/50 litre brew pot (diameter of 40cm or 16 inches) using a polyester grain bag to hold the grain.  This profile should be used with the BIAB mash profiles available in the BeerSmith mash profiles area.  The above assumes loose pellet hops and only clear, chilled wort transferred from the kettle using no trub management techniques. Experienced brewers should adjust &#39;Loss to Trub and Chiller&#39; and &#39;Brewhouse Efficiency&#39; accordingly to suit their trub management techniques.</NOTES>
 <DISPLAY_BOIL_SIZE>30.74 L</DISPLAY_BOIL_SIZE>
 <DISPLAY_BATCH_SIZE>18.93 L</DISPLAY_BATCH_SIZE>
 <DISPLAY_TUN_VOLUME>56.78 L</DISPLAY_TUN_VOLUME>
 <DISPLAY_TUN_WEIGHT>6.80 kg</DISPLAY_TUN_WEIGHT>
 <DISPLAY_TOP_UP_WATER>0.00 L</DISPLAY_TOP_UP_WATER>
 <DISPLAY_TRUB_CHILLER_LOSS>2.84 L</DISPLAY_TRUB_CHILLER_LOSS>
 <DISPLAY_LAUTER_DEADSPACE>0.00 L</DISPLAY_LAUTER_DEADSPACE>
 <DISPLAY_TOP_UP_KETTLE>0.00 L</DISPLAY_TOP_UP_KETTLE>
</EQUIPMENT>
<EQUIPMENT>
 <NAME>BREWTREE- 15 Gallon Brewing System</NAME>
 <VERSION>1</VERSION>
 <BOIL_SIZE>56.6771819</BOIL_SIZE>
 <BATCH_SIZE>56.7811768</BATCH_SIZE>
 <TUN_VOLUME>56.7811768</TUN_VOLUME>
 <TUN_WEIGHT>14.5149440</TUN_WEIGHT>
 <TUN_SPECIFIC_HEAT>0.1200000</TUN_SPECIFIC_HEAT>
 <TOP_UP_WATER>7.5708236</TOP_UP_WATER>
 <TRUB_CHILLER_LOSS>0.0000000</TRUB_CHILLER_LOSS>
 <EVAP_RATE>9.0000000</EVAP_RATE>
 <BOIL_TIME>60.0000000</BOIL_TIME>
 <CALC_BOIL_VOLUME>TRUE</CALC_BOIL_VOLUME>
 <LAUTER_DEADSPACE>1.8927059</LAUTER_DEADSPACE>
 <TOP_UP_KETTLE>0.0000000</TOP_UP_KETTLE>
 <HOP_UTILIZATION>100.0000000</HOP_UTILIZATION>
 <COOLING_LOSS_PCT>4.0000000</COOLING_LOSS_PCT>
 <NOTES>BREWTREE 15 gallon brewing system -- see www.brewtree.com</NOTES>
 <DISPLAY_BOIL_SIZE>56.68 L</DISPLAY_BOIL_SIZE>
 <DISPLAY_BATCH_SIZE>56.78 L</DISPLAY_BATCH_SIZE>
 <DISPLAY_TUN_VOLUME>56.78 L</DISPLAY_TUN_VOLUME>
 <DISPLAY_TUN_WEIGHT>14.51 kg</DISPLAY_TUN_WEIGHT>
 <DISPLAY_TOP_UP_WATER>7.57 L</DISPLAY_TOP_UP_WATER>
 <DISPLAY_TRUB_CHILLER_LOSS>0.00 L</DISPLAY_TRUB_CHILLER_LOSS>
 <DISPLAY_LAUTER_DEADSPACE>1.89 L</DISPLAY_LAUTER_DEADSPACE>
 <DISPLAY_TOP_UP_KETTLE>0.00 L</DISPLAY_TOP_UP_KETTLE>
</EQUIPMENT>
<EQUIPMENT>
 <NAME>Brew Pot  (2 Gallon)</NAME>
 <VERSION>1</VERSION>
 <BOIL_SIZE>6.0663650</BOIL_SIZE>
 <BATCH_SIZE>18.9270589</BATCH_SIZE>
 <TUN_VOLUME>7.5708236</TUN_VOLUME>
 <TUN_WEIGHT>1.1339800</TUN_WEIGHT>
 <TUN_SPECIFIC_HEAT>0.1200000</TUN_SPECIFIC_HEAT>
 <TOP_UP_WATER>14.1952942</TOP_UP_WATER>
 <TRUB_CHILLER_LOSS>0.0000000</TRUB_CHILLER_LOSS>
 <EVAP_RATE>9.0000000</EVAP_RATE>
 <BOIL_TIME>60.0000000</BOIL_TIME>
 <CALC_BOIL_VOLUME>TRUE</CALC_BOIL_VOLUME>
 <LAUTER_DEADSPACE>0.9463529</LAUTER_DEADSPACE>
 <TOP_UP_KETTLE>0.0000000</TOP_UP_KETTLE>
 <HOP_UTILIZATION>100.0000000</HOP_UTILIZATION>
 <COOLING_LOSS_PCT>4.0000000</COOLING_LOSS_PCT>
 <NOTES>Simple brew pot with 2 gallon capacity for extract brewing.  May also be used for partial mash with temperature or infusion mashing.</NOTES>
 <DISPLAY_BOIL_SIZE>6.07 L</DISPLAY_BOIL_SIZE>
 <DISPLAY_BATCH_SIZE>18.93 L</DISPLAY_BATCH_SIZE>
 <DISPLAY_TUN_VOLUME>7.57 L</DISPLAY_TUN_VOLUME>
 <DISPLAY_TUN_WEIGHT>1.13 kg</DISPLAY_TUN_WEIGHT>
 <DISPLAY_TOP_UP_WATER>14.20 L</DISPLAY_TOP_UP_WATER>
 <DISPLAY_TRUB_CHILLER_LOSS>0.00 L</DISPLAY_TRUB_CHILLER_LOSS>
 <DISPLAY_LAUTER_DEADSPACE>0.95 L</DISPLAY_LAUTER_DEADSPACE>
 <DISPLAY_TOP_UP_KETTLE>0.00 L</DISPLAY_TOP_UP_KETTLE>
</EQUIPMENT>
<EQUIPMENT>
 <NAME>Brew Pot  (3 Gallon)</NAME>
 <VERSION>1</VERSION>
 <BOIL_SIZE>9.1862099</BOIL_SIZE>
 <BATCH_SIZE>18.9270589</BATCH_SIZE>
 <TUN_VOLUME>11.3562354</TUN_VOLUME>
 <TUN_WEIGHT>1.3607760</TUN_WEIGHT>
 <TUN_SPECIFIC_HEAT>0.1200000</TUN_SPECIFIC_HEAT>
 <TOP_UP_WATER>11.3562354</TOP_UP_WATER>
 <TRUB_CHILLER_LOSS>0.0000000</TRUB_CHILLER_LOSS>
 <EVAP_RATE>9.0000000</EVAP_RATE>
 <BOIL_TIME>60.0000000</BOIL_TIME>
 <CALC_BOIL_VOLUME>TRUE</CALC_BOIL_VOLUME>
 <LAUTER_DEADSPACE>0.9463529</LAUTER_DEADSPACE>
 <TOP_UP_KETTLE>0.0000000</TOP_UP_KETTLE>
 <HOP_UTILIZATION>100.0000000</HOP_UTILIZATION>
 <COOLING_LOSS_PCT>4.0000000</COOLING_LOSS_PCT>
 <NOTES>Simple Brew Pot with a 3 Gallon Capacity - leaving a workable boil volume of around 2.5 gal.  Used for extract or partial mash brewing.</NOTES>
 <DISPLAY_BOIL_SIZE>9.19 L</DISPLAY_BOIL_SIZE>
 <DISPLAY_BATCH_SIZE>18.93 L</DISPLAY_BATCH_SIZE>
 <DISPLAY_TUN_VOLUME>11.36 L</DISPLAY_TUN_VOLUME>
 <DISPLAY_TUN_WEIGHT>1.36 kg</DISPLAY_TUN_WEIGHT>
 <DISPLAY_TOP_UP_WATER>11.36 L</DISPLAY_TOP_UP_WATER>
 <DISPLAY_TRUB_CHILLER_LOSS>0.00 L</DISPLAY_TRUB_CHILLER_LOSS>
 <DISPLAY_LAUTER_DEADSPACE>0.95 L</DISPLAY_LAUTER_DEADSPACE>
 <DISPLAY_TOP_UP_KETTLE>0.00 L</DISPLAY_TOP_UP_KETTLE>
</EQUIPMENT>
<EQUIPMENT>
 <NAME>Brew Pot  (4 Gallon)</NAME>
 <VERSION>1</VERSION>
 <BOIL_SIZE>12.3060548</BOIL_SIZE>
 <BATCH_SIZE>18.9270589</BATCH_SIZE>
 <TUN_VOLUME>15.1416471</TUN_VOLUME>
 <TUN_WEIGHT>1.8143680</TUN_WEIGHT>
 <TUN_SPECIFIC_HEAT>0.1200000</TUN_SPECIFIC_HEAT>
 <TOP_UP_WATER>8.5171765</TOP_UP_WATER>
 <TRUB_CHILLER_LOSS>0.0000000</TRUB_CHILLER_LOSS>
 <EVAP_RATE>9.0000000</EVAP_RATE>
 <BOIL_TIME>60.0000000</BOIL_TIME>
 <CALC_BOIL_VOLUME>TRUE</CALC_BOIL_VOLUME>
 <LAUTER_DEADSPACE>0.9463529</LAUTER_DEADSPACE>
 <TOP_UP_KETTLE>0.0000000</TOP_UP_KETTLE>
 <HOP_UTILIZATION>100.0000000</HOP_UTILIZATION>
 <COOLING_LOSS_PCT>4.0000000</COOLING_LOSS_PCT>
 <NOTES>Simple Brew Pot with a 4 Gallon Capacity - leaving a workable boil volume of around 3.25 gal.  Used for extract or partial mash brewing.</NOTES>
 <DISPLAY_BOIL_SIZE>12.31 L</DISPLAY_BOIL_SIZE>
 <DISPLAY_BATCH_SIZE>18.93 L</DISPLAY_BATCH_SIZE>
 <DISPLAY_TUN_VOLUME>15.14 L</DISPLAY_TUN_VOLUME>
 <DISPLAY_TUN_WEIGHT>1.81 kg</DISPLAY_TUN_WEIGHT>
 <DISPLAY_TOP_UP_WATER>8.52 L</DISPLAY_TOP_UP_WATER>
 <DISPLAY_TRUB_CHILLER_LOSS>0.00 L</DISPLAY_TRUB_CHILLER_LOSS>
 <DISPLAY_LAUTER_DEADSPACE>0.95 L</DISPLAY_LAUTER_DEADSPACE>
 <DISPLAY_TOP_UP_KETTLE>0.00 L</DISPLAY_TOP_UP_KETTLE>
</EQUIPMENT>
<EQUIPMENT>
 <NAME>Brew Pot  (5 Gallon)</NAME>
 <VERSION>1</VERSION>
 <BOIL_SIZE>15.4258997</BOIL_SIZE>
 <BATCH_SIZE>18.9270589</BATCH_SIZE>
 <TUN_VOLUME>18.9270589</TUN_VOLUME>
 <TUN_WEIGHT>2.2679600</TUN_WEIGHT>
 <TUN_SPECIFIC_HEAT>0.1200000</TUN_SPECIFIC_HEAT>
 <TOP_UP_WATER>6.6244706</TOP_UP_WATER>
 <TRUB_CHILLER_LOSS>0.9463529</TRUB_CHILLER_LOSS>
 <EVAP_RATE>9.0000000</EVAP_RATE>
 <BOIL_TIME>60.0000000</BOIL_TIME>
 <CALC_BOIL_VOLUME>TRUE</CALC_BOIL_VOLUME>
 <LAUTER_DEADSPACE>0.9463529</LAUTER_DEADSPACE>
 <TOP_UP_KETTLE>0.0000000</TOP_UP_KETTLE>
 <HOP_UTILIZATION>100.0000000</HOP_UTILIZATION>
 <COOLING_LOSS_PCT>4.0000000</COOLING_LOSS_PCT>
 <NOTES>Simple Brew Pot with a 5 Gallon Capacity - leaving a workable boil volume of around 4.25 gal.  Used for extract or partial mash brewing.</NOTES>
 <DISPLAY_BOIL_SIZE>15.43 L</DISPLAY_BOIL_SIZE>
 <DISPLAY_BATCH_SIZE>18.93 L</DISPLAY_BATCH_SIZE>
 <DISPLAY_TUN_VOLUME>18.93 L</DISPLAY_TUN_VOLUME>
 <DISPLAY_TUN_WEIGHT>2.27 kg</DISPLAY_TUN_WEIGHT>
 <DISPLAY_TOP_UP_WATER>6.62 L</DISPLAY_TOP_UP_WATER>
 <DISPLAY_TRUB_CHILLER_LOSS>0.95 L</DISPLAY_TRUB_CHILLER_LOSS>
 <DISPLAY_LAUTER_DEADSPACE>0.95 L</DISPLAY_LAUTER_DEADSPACE>
 <DISPLAY_TOP_UP_KETTLE>0.00 L</DISPLAY_TOP_UP_KETTLE>
</EQUIPMENT>
<EQUIPMENT>
 <NAME>Brew Pot  (6+gal) and Igloo/Gott Cooler (5 Gal)</NAME>
 <VERSION>1</VERSION>
 <BOIL_SIZE>22.7055377</BOIL_SIZE>
 <BATCH_SIZE>18.9270589</BATCH_SIZE>
 <TUN_VOLUME>18.9270589</TUN_VOLUME>
 <TUN_WEIGHT>1.8143680</TUN_WEIGHT>
 <TUN_SPECIFIC_HEAT>0.3000000</TUN_SPECIFIC_HEAT>
 <TOP_UP_WATER>0.0000000</TOP_UP_WATER>
 <TRUB_CHILLER_LOSS>0.9463529</TRUB_CHILLER_LOSS>
 <EVAP_RATE>9.0000000</EVAP_RATE>
 <BOIL_TIME>60.0000000</BOIL_TIME>
 <CALC_BOIL_VOLUME>TRUE</CALC_BOIL_VOLUME>
 <LAUTER_DEADSPACE>0.9463529</LAUTER_DEADSPACE>
 <TOP_UP_KETTLE>0.0000000</TOP_UP_KETTLE>
 <HOP_UTILIZATION>100.0000000</HOP_UTILIZATION>
 <COOLING_LOSS_PCT>4.0000000</COOLING_LOSS_PCT>
 <NOTES>Popular all grain setup.  5 Gallon Gott or Igloo cooler as mash tun with false bottom, and 7-9 gallon brewpot capable of boiling at least 6 gallons of wort.  Primarily used for single infusion mashes.</NOTES>
 <DISPLAY_BOIL_SIZE>22.71 L</DISPLAY_BOIL_SIZE>
 <DISPLAY_BATCH_SIZE>18.93 L</DISPLAY_BATCH_SIZE>
 <DISPLAY_TUN_VOLUME>18.93 L</DISPLAY_TUN_VOLUME>
 <DISPLAY_TUN_WEIGHT>1.81 kg</DISPLAY_TUN_WEIGHT>
 <DISPLAY_TOP_UP_WATER>0.00 L</DISPLAY_TOP_UP_WATER>
 <DISPLAY_TRUB_CHILLER_LOSS>0.95 L</DISPLAY_TRUB_CHILLER_LOSS>
 <DISPLAY_LAUTER_DEADSPACE>0.95 L</DISPLAY_LAUTER_DEADSPACE>
 <DISPLAY_TOP_UP_KETTLE>0.00 L</DISPLAY_TOP_UP_KETTLE>
</EQUIPMENT>
<EQUIPMENT>
 <NAME>Brew Pot (12.5 gal) and Igloo Cooler (10 Gal)</NAME>
 <VERSION>1</VERSION>
 <BOIL_SIZE>45.9156429</BOIL_SIZE>
 <BATCH_SIZE>37.8541178</BATCH_SIZE>
 <TUN_VOLUME>37.8541178</TUN_VOLUME>
 <TUN_WEIGHT>4.0823280</TUN_WEIGHT>
 <TUN_SPECIFIC_HEAT>0.3000000</TUN_SPECIFIC_HEAT>
 <TOP_UP_WATER>0.0000000</TOP_UP_WATER>
 <TRUB_CHILLER_LOSS>1.8927059</TRUB_CHILLER_LOSS>
 <EVAP_RATE>10.0000000</EVAP_RATE>
 <BOIL_TIME>60.0000000</BOIL_TIME>
 <CALC_BOIL_VOLUME>TRUE</CALC_BOIL_VOLUME>
 <LAUTER_DEADSPACE>0.9463529</LAUTER_DEADSPACE>
 <TOP_UP_KETTLE>0.0000000</TOP_UP_KETTLE>
 <HOP_UTILIZATION>100.0000000</HOP_UTILIZATION>
 <COOLING_LOSS_PCT>4.0000000</COOLING_LOSS_PCT>
 <NOTES>12.5 gallon Turkey Fryer with 10 Gal. Igloo Mash Tun</NOTES>
 <DISPLAY_BOIL_SIZE>45.92 L</DISPLAY_BOIL_SIZE>
 <DISPLAY_BATCH_SIZE>37.85 L</DISPLAY_BATCH_SIZE>
 <DISPLAY_TUN_VOLUME>37.85 L</DISPLAY_TUN_VOLUME>
 <DISPLAY_TUN_WEIGHT>4.08 kg</DISPLAY_TUN_WEIGHT>
 <DISPLAY_TOP_UP_WATER>0.00 L</DISPLAY_TOP_UP_WATER>
 <DISPLAY_TRUB_CHILLER_LOSS>1.89 L</DISPLAY_TRUB_CHILLER_LOSS>
 <DISPLAY_LAUTER_DEADSPACE>0.95 L</DISPLAY_LAUTER_DEADSPACE>
 <DISPLAY_TOP_UP_KETTLE>0.00 L</DISPLAY_TOP_UP_KETTLE>
</EQUIPMENT>
<EQUIPMENT>
 <NAME>Brew Pot (15 Gal) and Igloo/Gott Cooler (10 Gal)</NAME>
 <VERSION>1</VERSION>
 <BOIL_SIZE>47.4909720</BOIL_SIZE>
 <BATCH_SIZE>37.8541178</BATCH_SIZE>
 <TUN_VOLUME>37.8541178</TUN_VOLUME>
 <TUN_WEIGHT>4.0823280</TUN_WEIGHT>
 <TUN_SPECIFIC_HEAT>0.3000000</TUN_SPECIFIC_HEAT>
 <TOP_UP_WATER>0.0000000</TOP_UP_WATER>
 <TRUB_CHILLER_LOSS>3.7854118</TRUB_CHILLER_LOSS>
 <EVAP_RATE>9.0000000</EVAP_RATE>
 <BOIL_TIME>60.0000000</BOIL_TIME>
 <CALC_BOIL_VOLUME>TRUE</CALC_BOIL_VOLUME>
 <LAUTER_DEADSPACE>3.0283294</LAUTER_DEADSPACE>
 <TOP_UP_KETTLE>0.0000000</TOP_UP_KETTLE>
 <HOP_UTILIZATION>100.0000000</HOP_UTILIZATION>
 <COOLING_LOSS_PCT>4.0000000</COOLING_LOSS_PCT>
 <NOTES>Popular 10 gallon setup for all grain brewing.  Uses a 10 gallon water cooler as mash tun for single infusion mashes and a 15 gallon brew pot for full size boil of the 12+ gallons of wort.</NOTES>
 <DISPLAY_BOIL_SIZE>47.49 L</DISPLAY_BOIL_SIZE>
 <DISPLAY_BATCH_SIZE>37.85 L</DISPLAY_BATCH_SIZE>
 <DISPLAY_TUN_VOLUME>37.85 L</DISPLAY_TUN_VOLUME>
 <DISPLAY_TUN_WEIGHT>4.08 kg</DISPLAY_TUN_WEIGHT>
 <DISPLAY_TOP_UP_WATER>0.00 L</DISPLAY_TOP_UP_WATER>
 <DISPLAY_TRUB_CHILLER_LOSS>3.79 L</DISPLAY_TRUB_CHILLER_LOSS>
 <DISPLAY_LAUTER_DEADSPACE>3.03 L</DISPLAY_LAUTER_DEADSPACE>
 <DISPLAY_TOP_UP_KETTLE>0.00 L</DISPLAY_TOP_UP_KETTLE>
</EQUIPMENT>
<EQUIPMENT>
 <NAME>Brew Pot (7.5 gal) and Cooler (48 qt)</NAME>
 <VERSION>1</VERSION>
 <BOIL_SIZE>24.2790924</BOIL_SIZE>
 <BATCH_SIZE>18.9270589</BATCH_SIZE>
 <TUN_VOLUME>45.4249414</TUN_VOLUME>
 <TUN_WEIGHT>4.0823280</TUN_WEIGHT>
 <TUN_SPECIFIC_HEAT>0.3000000</TUN_SPECIFIC_HEAT>
 <TOP_UP_WATER>0.0000000</TOP_UP_WATER>
 <TRUB_CHILLER_LOSS>1.8927059</TRUB_CHILLER_LOSS>
 <EVAP_RATE>11.0000000</EVAP_RATE>
 <BOIL_TIME>60.0000000</BOIL_TIME>
 <CALC_BOIL_VOLUME>TRUE</CALC_BOIL_VOLUME>
 <LAUTER_DEADSPACE>0.9463529</LAUTER_DEADSPACE>
 <TOP_UP_KETTLE>0.0000000</TOP_UP_KETTLE>
 <HOP_UTILIZATION>100.0000000</HOP_UTILIZATION>
 <COOLING_LOSS_PCT>4.0000000</COOLING_LOSS_PCT>
 <NOTES>30 qt (7.5 gal) Turkey Fryer with 48 qt cooler Mash Tun</NOTES>
 <DISPLAY_BOIL_SIZE>24.28 L</DISPLAY_BOIL_SIZE>
 <DISPLAY_BATCH_SIZE>18.93 L</DISPLAY_BATCH_SIZE>
 <DISPLAY_TUN_VOLUME>45.42 L</DISPLAY_TUN_VOLUME>
 <DISPLAY_TUN_WEIGHT>4.08 kg</DISPLAY_TUN_WEIGHT>
 <DISPLAY_TOP_UP_WATER>0.00 L</DISPLAY_TOP_UP_WATER>
 <DISPLAY_TRUB_CHILLER_LOSS>1.89 L</DISPLAY_TRUB_CHILLER_LOSS>
 <DISPLAY_LAUTER_DEADSPACE>0.95 L</DISPLAY_LAUTER_DEADSPACE>
 <DISPLAY_TOP_UP_KETTLE>0.00 L</DISPLAY_TOP_UP_KETTLE>
</EQUIPMENT>
<EQUIPMENT>
 <NAME>Brew Pot (7.5 gal) and Igloo Cooler (10 Gal)</NAME>
 <VERSION>1</VERSION>
 <BOIL_SIZE>24.2790924</BOIL_SIZE>
 <BATCH_SIZE>18.9270589</BATCH_SIZE>
 <TUN_VOLUME>37.8541178</TUN_VOLUME>
 <TUN_WEIGHT>4.0823280</TUN_WEIGHT>
 <TUN_SPECIFIC_HEAT>0.3000000</TUN_SPECIFIC_HEAT>
 <TOP_UP_WATER>0.0000000</TOP_UP_WATER>
 <TRUB_CHILLER_LOSS>1.8927059</TRUB_CHILLER_LOSS>
 <EVAP_RATE>11.0000000</EVAP_RATE>
 <BOIL_TIME>60.0000000</BOIL_TIME>
 <CALC_BOIL_VOLUME>TRUE</CALC_BOIL_VOLUME>
 <LAUTER_DEADSPACE>0.9463529</LAUTER_DEADSPACE>
 <TOP_UP_KETTLE>0.0000000</TOP_UP_KETTLE>
 <HOP_UTILIZATION>100.0000000</HOP_UTILIZATION>
 <COOLING_LOSS_PCT>4.0000000</COOLING_LOSS_PCT>
 <NOTES>30 qt (7.5 gal) Turkey Fryer with 10 Gal. Igloo Mash Tun</NOTES>
 <DISPLAY_BOIL_SIZE>24.28 L</DISPLAY_BOIL_SIZE>
 <DISPLAY_BATCH_SIZE>18.93 L</DISPLAY_BATCH_SIZE>
 <DISPLAY_TUN_VOLUME>37.85 L</DISPLAY_TUN_VOLUME>
 <DISPLAY_TUN_WEIGHT>4.08 kg</DISPLAY_TUN_WEIGHT>
 <DISPLAY_TOP_UP_WATER>0.00 L</DISPLAY_TOP_UP_WATER>
 <DISPLAY_TRUB_CHILLER_LOSS>1.89 L</DISPLAY_TRUB_CHILLER_LOSS>
 <DISPLAY_LAUTER_DEADSPACE>0.95 L</DISPLAY_LAUTER_DEADSPACE>
 <DISPLAY_TOP_UP_KETTLE>0.00 L</DISPLAY_TOP_UP_KETTLE>
</EQUIPMENT>
<EQUIPMENT>
 <NAME>Cider - Large 10 Gal/38 l Batch</NAME>
 <VERSION>1</VERSION>
 <BOIL_SIZE>41.3240786</BOIL_SIZE>
 <BATCH_SIZE>37.8541178</BATCH_SIZE>
 <TUN_VOLUME>18.9270589</TUN_VOLUME>
 <TUN_WEIGHT>4.5359200</TUN_WEIGHT>
 <TUN_SPECIFIC_HEAT>0.3000000</TUN_SPECIFIC_HEAT>
 <TOP_UP_WATER>0.0000000</TOP_UP_WATER>
 <TRUB_CHILLER_LOSS>0.0000000</TRUB_CHILLER_LOSS>
 <EVAP_RATE>4.5801527</EVAP_RATE>
 <BOIL_TIME>60.0000000</BOIL_TIME>
 <CALC_BOIL_VOLUME>TRUE</CALC_BOIL_VOLUME>
 <LAUTER_DEADSPACE>0.0000000</LAUTER_DEADSPACE>
 <TOP_UP_KETTLE>0.0000000</TOP_UP_KETTLE>
 <HOP_UTILIZATION>100.0000000</HOP_UTILIZATION>
 <COOLING_LOSS_PCT>4.0000000</COOLING_LOSS_PCT>
 <NOTES>Double size 10 gal/38 liter setup for no-boil cider.  Typically the primary fermenter is a large plastic bucket or fermenter for easy of access.  Cider is often aged in a carboy or keg.</NOTES>
 <DISPLAY_BOIL_SIZE>41.32 L</DISPLAY_BOIL_SIZE>
 <DISPLAY_BATCH_SIZE>37.85 L</DISPLAY_BATCH_SIZE>
 <DISPLAY_TUN_VOLUME>18.93 L</DISPLAY_TUN_VOLUME>
 <DISPLAY_TUN_WEIGHT>4.54 kg</DISPLAY_TUN_WEIGHT>
 <DISPLAY_TOP_UP_WATER>0.00 L</DISPLAY_TOP_UP_WATER>
 <DISPLAY_TRUB_CHILLER_LOSS>0.00 L</DISPLAY_TRUB_CHILLER_LOSS>
 <DISPLAY_LAUTER_DEADSPACE>0.00 L</DISPLAY_LAUTER_DEADSPACE>
 <DISPLAY_TOP_UP_KETTLE>0.00 L</DISPLAY_TOP_UP_KETTLE>
</EQUIPMENT>
<EQUIPMENT>
 <NAME>Cider - Mini 3 Gal/11.3 l Batch</NAME>
 <VERSION>1</VERSION>
 <BOIL_SIZE>13.7221177</BOIL_SIZE>
 <BATCH_SIZE>11.3562354</BATCH_SIZE>
 <TUN_VOLUME>18.9270589</TUN_VOLUME>
 <TUN_WEIGHT>4.5359200</TUN_WEIGHT>
 <TUN_SPECIFIC_HEAT>0.3000000</TUN_SPECIFIC_HEAT>
 <TOP_UP_WATER>0.0000000</TOP_UP_WATER>
 <TRUB_CHILLER_LOSS>0.0000000</TRUB_CHILLER_LOSS>
 <EVAP_RATE>13.7931034</EVAP_RATE>
 <BOIL_TIME>60.0000000</BOIL_TIME>
 <CALC_BOIL_VOLUME>TRUE</CALC_BOIL_VOLUME>
 <LAUTER_DEADSPACE>0.0000000</LAUTER_DEADSPACE>
 <TOP_UP_KETTLE>0.0000000</TOP_UP_KETTLE>
 <HOP_UTILIZATION>100.0000000</HOP_UTILIZATION>
 <COOLING_LOSS_PCT>4.0000000</COOLING_LOSS_PCT>
 <NOTES>Mini 3 Gal/11.3 setup for no-boil cider.  Typically the primary fermenter is a  5 gal/19 l or larger plastic bucket for easy of access.  Cider is often aged in a carboy or keg.</NOTES>
 <DISPLAY_BOIL_SIZE>13.72 L</DISPLAY_BOIL_SIZE>
 <DISPLAY_BATCH_SIZE>11.36 L</DISPLAY_BATCH_SIZE>
 <DISPLAY_TUN_VOLUME>18.93 L</DISPLAY_TUN_VOLUME>
 <DISPLAY_TUN_WEIGHT>4.54 kg</DISPLAY_TUN_WEIGHT>
 <DISPLAY_TOP_UP_WATER>0.00 L</DISPLAY_TOP_UP_WATER>
 <DISPLAY_TRUB_CHILLER_LOSS>0.00 L</DISPLAY_TRUB_CHILLER_LOSS>
 <DISPLAY_LAUTER_DEADSPACE>0.00 L</DISPLAY_LAUTER_DEADSPACE>
 <DISPLAY_TOP_UP_KETTLE>0.00 L</DISPLAY_TOP_UP_KETTLE>
</EQUIPMENT>
<EQUIPMENT>
 <NAME>Cider - Standard 5 Gal/19 l Batch</NAME>
 <VERSION>1</VERSION>
 <BOIL_SIZE>21.6083923</BOIL_SIZE>
 <BATCH_SIZE>18.9270589</BATCH_SIZE>
 <TUN_VOLUME>18.9270589</TUN_VOLUME>
 <TUN_WEIGHT>4.5359200</TUN_WEIGHT>
 <TUN_SPECIFIC_HEAT>0.3000000</TUN_SPECIFIC_HEAT>
 <TOP_UP_WATER>0.0000000</TOP_UP_WATER>
 <TRUB_CHILLER_LOSS>0.0000000</TRUB_CHILLER_LOSS>
 <EVAP_RATE>8.7591241</EVAP_RATE>
 <BOIL_TIME>60.0000000</BOIL_TIME>
 <CALC_BOIL_VOLUME>TRUE</CALC_BOIL_VOLUME>
 <LAUTER_DEADSPACE>0.0000000</LAUTER_DEADSPACE>
 <TOP_UP_KETTLE>0.0000000</TOP_UP_KETTLE>
 <HOP_UTILIZATION>100.0000000</HOP_UTILIZATION>
 <COOLING_LOSS_PCT>4.0000000</COOLING_LOSS_PCT>
 <NOTES>Standard 5 gal/19 liter setup for no-boil cider.  Typically the primary fermenter is a 7.5 gal/28 l or larger plastic bucket for easy of access.  Cider is often aged in a carboy or keg.</NOTES>
 <DISPLAY_BOIL_SIZE>21.61 L</DISPLAY_BOIL_SIZE>
 <DISPLAY_BATCH_SIZE>18.93 L</DISPLAY_BATCH_SIZE>
 <DISPLAY_TUN_VOLUME>18.93 L</DISPLAY_TUN_VOLUME>
 <DISPLAY_TUN_WEIGHT>4.54 kg</DISPLAY_TUN_WEIGHT>
 <DISPLAY_TOP_UP_WATER>0.00 L</DISPLAY_TOP_UP_WATER>
 <DISPLAY_TRUB_CHILLER_LOSS>0.00 L</DISPLAY_TRUB_CHILLER_LOSS>
 <DISPLAY_LAUTER_DEADSPACE>0.00 L</DISPLAY_LAUTER_DEADSPACE>
 <DISPLAY_TOP_UP_KETTLE>0.00 L</DISPLAY_TOP_UP_KETTLE>
</EQUIPMENT>
<EQUIPMENT>
 <NAME>Dad Equipment</NAME>
 <VERSION>1</VERSION>
 <BOIL_SIZE>26.9998444</BOIL_SIZE>
 <BATCH_SIZE>23.9998617</BATCH_SIZE>
 <TUN_VOLUME>24.9998559</TUN_VOLUME>
 <TUN_WEIGHT>0.9999994</TUN_WEIGHT>
 <TUN_SPECIFIC_HEAT>0.3000000</TUN_SPECIFIC_HEAT>
 <TOP_UP_WATER>0.0000000</TOP_UP_WATER>
 <TRUB_CHILLER_LOSS>0.0000000</TRUB_CHILLER_LOSS>
 <EVAP_RATE>7.4074074</EVAP_RATE>
 <BOIL_TIME>60.0000000</BOIL_TIME>
 <CALC_BOIL_VOLUME>TRUE</CALC_BOIL_VOLUME>
 <LAUTER_DEADSPACE>0.0000000</LAUTER_DEADSPACE>
 <TOP_UP_KETTLE>0.0000000</TOP_UP_KETTLE>
 <HOP_UTILIZATION>100.0000000</HOP_UTILIZATION>
 <COOLING_LOSS_PCT>4.0000000</COOLING_LOSS_PCT>
 <NOTES></NOTES>
 <DISPLAY_BOIL_SIZE>27.00 L</DISPLAY_BOIL_SIZE>
 <DISPLAY_BATCH_SIZE>24.00 L</DISPLAY_BATCH_SIZE>
 <DISPLAY_TUN_VOLUME>25.00 L</DISPLAY_TUN_VOLUME>
 <DISPLAY_TUN_WEIGHT>1.00 kg</DISPLAY_TUN_WEIGHT>
 <DISPLAY_TOP_UP_WATER>0.00 L</DISPLAY_TOP_UP_WATER>
 <DISPLAY_TRUB_CHILLER_LOSS>0.00 L</DISPLAY_TRUB_CHILLER_LOSS>
 <DISPLAY_LAUTER_DEADSPACE>0.00 L</DISPLAY_LAUTER_DEADSPACE>
 <DISPLAY_TOP_UP_KETTLE>0.00 L</DISPLAY_TOP_UP_KETTLE>
</EQUIPMENT>
<EQUIPMENT>
 <NAME>Electric Urn (10 Gal/40 L) - BIAB</NAME>
 <VERSION>1</VERSION>
 <BOIL_SIZE>30.3398251</BOIL_SIZE>
 <BATCH_SIZE>18.9998905</BATCH_SIZE>
 <TUN_VOLUME>39.9997695</TUN_VOLUME>
 <TUN_WEIGHT>4.4996363</TUN_WEIGHT>
 <TUN_SPECIFIC_HEAT>0.3000000</TUN_SPECIFIC_HEAT>
 <TOP_UP_WATER>0.0000000</TOP_UP_WATER>
 <TRUB_CHILLER_LOSS>3.1699817</TRUB_CHILLER_LOSS>
 <EVAP_RATE>15.9964843</EVAP_RATE>
 <BOIL_TIME>90.0000000</BOIL_TIME>
 <CALC_BOIL_VOLUME>TRUE</CALC_BOIL_VOLUME>
 <LAUTER_DEADSPACE>0.0000000</LAUTER_DEADSPACE>
 <TOP_UP_KETTLE>0.0000000</TOP_UP_KETTLE>
 <HOP_UTILIZATION>100.0000000</HOP_UTILIZATION>
 <COOLING_LOSS_PCT>4.0000000</COOLING_LOSS_PCT>
 <NOTES>Sample Brew-In-A-Bag equipment profile set up for a 40 litre electric urn (diameter of 38cm or 15 inches) using a polyester grain bag to hold the grain.  This profile should be used with the BIAB mash profiles available in the BeerSmith mash profiles area. The above assumes loose pellet hops and only clear, chilled wort transferred from the kettle using no trub management techniques. Experienced brewers should adjust &#39;Loss to Trub and Chiller&#39; and &#39;Brewhouse Efficiency&#39; accordingly to suit their trub management techniques.</NOTES>
 <DISPLAY_BOIL_SIZE>30.34 L</DISPLAY_BOIL_SIZE>
 <DISPLAY_BATCH_SIZE>19.00 L</DISPLAY_BATCH_SIZE>
 <DISPLAY_TUN_VOLUME>40.00 L</DISPLAY_TUN_VOLUME>
 <DISPLAY_TUN_WEIGHT>4.50 kg</DISPLAY_TUN_WEIGHT>
 <DISPLAY_TOP_UP_WATER>0.00 L</DISPLAY_TOP_UP_WATER>
 <DISPLAY_TRUB_CHILLER_LOSS>3.17 L</DISPLAY_TRUB_CHILLER_LOSS>
 <DISPLAY_LAUTER_DEADSPACE>0.00 L</DISPLAY_LAUTER_DEADSPACE>
 <DISPLAY_TOP_UP_KETTLE>0.00 L</DISPLAY_TOP_UP_KETTLE>
</EQUIPMENT>
<EQUIPMENT>
 <NAME>Extract - Large 10 Gal/38 l Batch</NAME>
 <VERSION>1</VERSION>
 <BOIL_SIZE>33.2800786</BOIL_SIZE>
 <BATCH_SIZE>37.8541178</BATCH_SIZE>
 <TUN_VOLUME>56.7811768</TUN_VOLUME>
 <TUN_WEIGHT>9.0718400</TUN_WEIGHT>
 <TUN_SPECIFIC_HEAT>0.1500000</TUN_SPECIFIC_HEAT>
 <TOP_UP_WATER>15.1416471</TOP_UP_WATER>
 <TRUB_CHILLER_LOSS>3.7854118</TRUB_CHILLER_LOSS>
 <EVAP_RATE>17.0616114</EVAP_RATE>
 <BOIL_TIME>60.0000000</BOIL_TIME>
 <CALC_BOIL_VOLUME>TRUE</CALC_BOIL_VOLUME>
 <LAUTER_DEADSPACE>3.7854118</LAUTER_DEADSPACE>
 <TOP_UP_KETTLE>0.0000000</TOP_UP_KETTLE>
 <HOP_UTILIZATION>100.0000000</HOP_UTILIZATION>
 <COOLING_LOSS_PCT>4.0000000</COOLING_LOSS_PCT>
 <NOTES>Large 10 gal/38 l batch setup for all extract brewing.  Uses 10 gal boil pot and 4 gal of top up water to avoid boil-overs.</NOTES>
 <DISPLAY_BOIL_SIZE>33.28 L</DISPLAY_BOIL_SIZE>
 <DISPLAY_BATCH_SIZE>37.85 L</DISPLAY_BATCH_SIZE>
 <DISPLAY_TUN_VOLUME>56.78 L</DISPLAY_TUN_VOLUME>
 <DISPLAY_TUN_WEIGHT>9.07 kg</DISPLAY_TUN_WEIGHT>
 <DISPLAY_TOP_UP_WATER>15.14 L</DISPLAY_TOP_UP_WATER>
 <DISPLAY_TRUB_CHILLER_LOSS>3.79 L</DISPLAY_TRUB_CHILLER_LOSS>
 <DISPLAY_LAUTER_DEADSPACE>3.79 L</DISPLAY_LAUTER_DEADSPACE>
 <DISPLAY_TOP_UP_KETTLE>0.00 L</DISPLAY_TOP_UP_KETTLE>
</EQUIPMENT>
<EQUIPMENT>
 <NAME>Extract - Mini 3 Gal/11.3 l Batch</NAME>
 <VERSION>1</VERSION>
 <BOIL_SIZE>10.0076824</BOIL_SIZE>
 <BATCH_SIZE>11.3562354</BATCH_SIZE>
 <TUN_VOLUME>11.3562354</TUN_VOLUME>
 <TUN_WEIGHT>1.3607760</TUN_WEIGHT>
 <TUN_SPECIFIC_HEAT>0.1200000</TUN_SPECIFIC_HEAT>
 <TOP_UP_WATER>3.7854118</TOP_UP_WATER>
 <TRUB_CHILLER_LOSS>0.9463529</TRUB_CHILLER_LOSS>
 <EVAP_RATE>11.3475177</EVAP_RATE>
 <BOIL_TIME>60.0000000</BOIL_TIME>
 <CALC_BOIL_VOLUME>TRUE</CALC_BOIL_VOLUME>
 <LAUTER_DEADSPACE>0.0000000</LAUTER_DEADSPACE>
 <TOP_UP_KETTLE>0.0000000</TOP_UP_KETTLE>
 <HOP_UTILIZATION>100.0000000</HOP_UTILIZATION>
 <COOLING_LOSS_PCT>4.0000000</COOLING_LOSS_PCT>
 <NOTES>Extract batch with a 3 gal/11l target batch volume designed to fit in a 3 gal pot.  Uses about 1 gal/4 liters of top-up water.</NOTES>
 <DISPLAY_BOIL_SIZE>10.01 L</DISPLAY_BOIL_SIZE>
 <DISPLAY_BATCH_SIZE>11.36 L</DISPLAY_BATCH_SIZE>
 <DISPLAY_TUN_VOLUME>11.36 L</DISPLAY_TUN_VOLUME>
 <DISPLAY_TUN_WEIGHT>1.36 kg</DISPLAY_TUN_WEIGHT>
 <DISPLAY_TOP_UP_WATER>3.79 L</DISPLAY_TOP_UP_WATER>
 <DISPLAY_TRUB_CHILLER_LOSS>0.95 L</DISPLAY_TRUB_CHILLER_LOSS>
 <DISPLAY_LAUTER_DEADSPACE>0.00 L</DISPLAY_LAUTER_DEADSPACE>
 <DISPLAY_TOP_UP_KETTLE>0.00 L</DISPLAY_TOP_UP_KETTLE>
</EQUIPMENT>
<EQUIPMENT>
 <NAME>Extract - Standard 5 Gal/19 l Batch</NAME>
 <VERSION>1</VERSION>
 <BOIL_SIZE>16.1873671</BOIL_SIZE>
 <BATCH_SIZE>18.9270589</BATCH_SIZE>
 <TUN_VOLUME>18.9270589</TUN_VOLUME>
 <TUN_WEIGHT>2.2679600</TUN_WEIGHT>
 <TUN_SPECIFIC_HEAT>0.1200000</TUN_SPECIFIC_HEAT>
 <TOP_UP_WATER>7.5708236</TOP_UP_WATER>
 <TRUB_CHILLER_LOSS>2.8390588</TRUB_CHILLER_LOSS>
 <EVAP_RATE>8.6524408</EVAP_RATE>
 <BOIL_TIME>60.0000000</BOIL_TIME>
 <CALC_BOIL_VOLUME>TRUE</CALC_BOIL_VOLUME>
 <LAUTER_DEADSPACE>0.9463529</LAUTER_DEADSPACE>
 <TOP_UP_KETTLE>0.0000000</TOP_UP_KETTLE>
 <HOP_UTILIZATION>100.0000000</HOP_UTILIZATION>
 <COOLING_LOSS_PCT>4.0000000</COOLING_LOSS_PCT>
 <NOTES>Extract Setup for 5 gal/19 l brew pot - leaving a workable boil volume of around 4.5 gal.   Used for extract or partial mash brewing.  Note top-up water is still required as we can&#39;t reach a full volume boil in this setup.</NOTES>
 <DISPLAY_BOIL_SIZE>16.19 L</DISPLAY_BOIL_SIZE>
 <DISPLAY_BATCH_SIZE>18.93 L</DISPLAY_BATCH_SIZE>
 <DISPLAY_TUN_VOLUME>18.93 L</DISPLAY_TUN_VOLUME>
 <DISPLAY_TUN_WEIGHT>2.27 kg</DISPLAY_TUN_WEIGHT>
 <DISPLAY_TOP_UP_WATER>7.57 L</DISPLAY_TOP_UP_WATER>
 <DISPLAY_TRUB_CHILLER_LOSS>2.84 L</DISPLAY_TRUB_CHILLER_LOSS>
 <DISPLAY_LAUTER_DEADSPACE>0.95 L</DISPLAY_LAUTER_DEADSPACE>
 <DISPLAY_TOP_UP_KETTLE>0.00 L</DISPLAY_TOP_UP_KETTLE>
</EQUIPMENT>
<EQUIPMENT>
 <NAME>Kit Beer No Boil</NAME>
 <VERSION>1</VERSION>
 <BOIL_SIZE>0.0000000</BOIL_SIZE>
 <BATCH_SIZE>22.9998674</BATCH_SIZE>
 <TUN_VOLUME>0.0000000</TUN_VOLUME>
 <TUN_WEIGHT>0.0000000</TUN_WEIGHT>
 <TUN_SPECIFIC_HEAT>0.2150000</TUN_SPECIFIC_HEAT>
 <TOP_UP_WATER>0.0000000</TOP_UP_WATER>
 <TRUB_CHILLER_LOSS>0.0000000</TRUB_CHILLER_LOSS>
 <EVAP_RATE>0.0000000</EVAP_RATE>
 <BOIL_TIME>0.0000000</BOIL_TIME>
 <CALC_BOIL_VOLUME>FALSE</CALC_BOIL_VOLUME>
 <LAUTER_DEADSPACE>0.0000000</LAUTER_DEADSPACE>
 <TOP_UP_KETTLE>0.0000000</TOP_UP_KETTLE>
 <HOP_UTILIZATION>100.0000000</HOP_UTILIZATION>
 <COOLING_LOSS_PCT>0.0000000</COOLING_LOSS_PCT>
 <NOTES></NOTES>
 <DISPLAY_BOIL_SIZE>0.00 L</DISPLAY_BOIL_SIZE>
 <DISPLAY_BATCH_SIZE>23.00 L</DISPLAY_BATCH_SIZE>
 <DISPLAY_TUN_VOLUME>0.00 L</DISPLAY_TUN_VOLUME>
 <DISPLAY_TUN_WEIGHT>0.00 kg</DISPLAY_TUN_WEIGHT>
 <DISPLAY_TOP_UP_WATER>0.00 L</DISPLAY_TOP_UP_WATER>
 <DISPLAY_TRUB_CHILLER_LOSS>0.00 L</DISPLAY_TRUB_CHILLER_LOSS>
 <DISPLAY_LAUTER_DEADSPACE>0.00 L</DISPLAY_LAUTER_DEADSPACE>
 <DISPLAY_TOP_UP_KETTLE>0.00 L</DISPLAY_TOP_UP_KETTLE>
</EQUIPMENT>
<EQUIPMENT>
 <NAME>Mead - Large 10 Gal/38 l Batch</NAME>
 <VERSION>1</VERSION>
 <BOIL_SIZE>41.3240786</BOIL_SIZE>
 <BATCH_SIZE>37.8541178</BATCH_SIZE>
 <TUN_VOLUME>18.9270589</TUN_VOLUME>
 <TUN_WEIGHT>4.5359200</TUN_WEIGHT>
 <TUN_SPECIFIC_HEAT>0.3000000</TUN_SPECIFIC_HEAT>
 <TOP_UP_WATER>0.0000000</TOP_UP_WATER>
 <TRUB_CHILLER_LOSS>0.0000000</TRUB_CHILLER_LOSS>
 <EVAP_RATE>4.5801527</EVAP_RATE>
 <BOIL_TIME>60.0000000</BOIL_TIME>
 <CALC_BOIL_VOLUME>TRUE</CALC_BOIL_VOLUME>
 <LAUTER_DEADSPACE>0.0000000</LAUTER_DEADSPACE>
 <TOP_UP_KETTLE>0.0000000</TOP_UP_KETTLE>
 <HOP_UTILIZATION>100.0000000</HOP_UTILIZATION>
 <COOLING_LOSS_PCT>4.0000000</COOLING_LOSS_PCT>
 <NOTES>Mead setup for the serious mead maker fermenting 10 gal/38 l at a time.  No boil method.  Uses 15 Gal bucket or keg for primary fermentation and carboys or kegs for aging.</NOTES>
 <DISPLAY_BOIL_SIZE>41.32 L</DISPLAY_BOIL_SIZE>
 <DISPLAY_BATCH_SIZE>37.85 L</DISPLAY_BATCH_SIZE>
 <DISPLAY_TUN_VOLUME>18.93 L</DISPLAY_TUN_VOLUME>
 <DISPLAY_TUN_WEIGHT>4.54 kg</DISPLAY_TUN_WEIGHT>
 <DISPLAY_TOP_UP_WATER>0.00 L</DISPLAY_TOP_UP_WATER>
 <DISPLAY_TRUB_CHILLER_LOSS>0.00 L</DISPLAY_TRUB_CHILLER_LOSS>
 <DISPLAY_LAUTER_DEADSPACE>0.00 L</DISPLAY_LAUTER_DEADSPACE>
 <DISPLAY_TOP_UP_KETTLE>0.00 L</DISPLAY_TOP_UP_KETTLE>
</EQUIPMENT>
<EQUIPMENT>
 <NAME>Mead - Micro 1 Gal/4 l Batch</NAME>
 <VERSION>1</VERSION>
 <BOIL_SIZE>5.8358432</BOIL_SIZE>
 <BATCH_SIZE>3.7854118</BATCH_SIZE>
 <TUN_VOLUME>18.9270589</TUN_VOLUME>
 <TUN_WEIGHT>4.5359200</TUN_WEIGHT>
 <TUN_SPECIFIC_HEAT>0.3000000</TUN_SPECIFIC_HEAT>
 <TOP_UP_WATER>0.0000000</TOP_UP_WATER>
 <TRUB_CHILLER_LOSS>0.0000000</TRUB_CHILLER_LOSS>
 <EVAP_RATE>32.4324324</EVAP_RATE>
 <BOIL_TIME>60.0000000</BOIL_TIME>
 <CALC_BOIL_VOLUME>TRUE</CALC_BOIL_VOLUME>
 <LAUTER_DEADSPACE>0.0000000</LAUTER_DEADSPACE>
 <TOP_UP_KETTLE>0.0000000</TOP_UP_KETTLE>
 <HOP_UTILIZATION>100.0000000</HOP_UTILIZATION>
 <COOLING_LOSS_PCT>4.0000000</COOLING_LOSS_PCT>
 <NOTES>Tiny 1 gal/4 liter mead setup.  No boil method.  Primary fermentation is done in a small 1.5-2 gal (6-8 l) bucket.  Secondary and later fermentation is done in a 1 gal/4 l glass jug.</NOTES>
 <DISPLAY_BOIL_SIZE>5.84 L</DISPLAY_BOIL_SIZE>
 <DISPLAY_BATCH_SIZE>3.79 L</DISPLAY_BATCH_SIZE>
 <DISPLAY_TUN_VOLUME>18.93 L</DISPLAY_TUN_VOLUME>
 <DISPLAY_TUN_WEIGHT>4.54 kg</DISPLAY_TUN_WEIGHT>
 <DISPLAY_TOP_UP_WATER>0.00 L</DISPLAY_TOP_UP_WATER>
 <DISPLAY_TRUB_CHILLER_LOSS>0.00 L</DISPLAY_TRUB_CHILLER_LOSS>
 <DISPLAY_LAUTER_DEADSPACE>0.00 L</DISPLAY_LAUTER_DEADSPACE>
 <DISPLAY_TOP_UP_KETTLE>0.00 L</DISPLAY_TOP_UP_KETTLE>
</EQUIPMENT>
<EQUIPMENT>
 <NAME>Mead - Mini 3 Gal/11.3 l Batch</NAME>
 <VERSION>1</VERSION>
 <BOIL_SIZE>13.7221177</BOIL_SIZE>
 <BATCH_SIZE>11.3562354</BATCH_SIZE>
 <TUN_VOLUME>18.9270589</TUN_VOLUME>
 <TUN_WEIGHT>4.5359200</TUN_WEIGHT>
 <TUN_SPECIFIC_HEAT>0.3000000</TUN_SPECIFIC_HEAT>
 <TOP_UP_WATER>0.0000000</TOP_UP_WATER>
 <TRUB_CHILLER_LOSS>0.0000000</TRUB_CHILLER_LOSS>
 <EVAP_RATE>13.7931034</EVAP_RATE>
 <BOIL_TIME>60.0000000</BOIL_TIME>
 <CALC_BOIL_VOLUME>TRUE</CALC_BOIL_VOLUME>
 <LAUTER_DEADSPACE>0.0000000</LAUTER_DEADSPACE>
 <TOP_UP_KETTLE>0.0000000</TOP_UP_KETTLE>
 <HOP_UTILIZATION>100.0000000</HOP_UTILIZATION>
 <COOLING_LOSS_PCT>4.0000000</COOLING_LOSS_PCT>
 <NOTES>Mead mini batch with a 3 gal/11.3 l starting volume and no-boil method.  Primary fermentation is usually done in a 5 gal/19 l bucket, and secondary is often done in glass or mini-kegs to avoid oxygen during longer aging periods.</NOTES>
 <DISPLAY_BOIL_SIZE>13.72 L</DISPLAY_BOIL_SIZE>
 <DISPLAY_BATCH_SIZE>11.36 L</DISPLAY_BATCH_SIZE>
 <DISPLAY_TUN_VOLUME>18.93 L</DISPLAY_TUN_VOLUME>
 <DISPLAY_TUN_WEIGHT>4.54 kg</DISPLAY_TUN_WEIGHT>
 <DISPLAY_TOP_UP_WATER>0.00 L</DISPLAY_TOP_UP_WATER>
 <DISPLAY_TRUB_CHILLER_LOSS>0.00 L</DISPLAY_TRUB_CHILLER_LOSS>
 <DISPLAY_LAUTER_DEADSPACE>0.00 L</DISPLAY_LAUTER_DEADSPACE>
 <DISPLAY_TOP_UP_KETTLE>0.00 L</DISPLAY_TOP_UP_KETTLE>
</EQUIPMENT>
<EQUIPMENT>
 <NAME>Mead - Standard 5 Gal/19 l Batch</NAME>
 <VERSION>1</VERSION>
 <BOIL_SIZE>21.6083923</BOIL_SIZE>
 <BATCH_SIZE>18.9270589</BATCH_SIZE>
 <TUN_VOLUME>18.9270589</TUN_VOLUME>
 <TUN_WEIGHT>4.5359200</TUN_WEIGHT>
 <TUN_SPECIFIC_HEAT>0.3000000</TUN_SPECIFIC_HEAT>
 <TOP_UP_WATER>0.0000000</TOP_UP_WATER>
 <TRUB_CHILLER_LOSS>0.0000000</TRUB_CHILLER_LOSS>
 <EVAP_RATE>8.7591241</EVAP_RATE>
 <BOIL_TIME>60.0000000</BOIL_TIME>
 <CALC_BOIL_VOLUME>TRUE</CALC_BOIL_VOLUME>
 <LAUTER_DEADSPACE>0.0000000</LAUTER_DEADSPACE>
 <TOP_UP_KETTLE>0.0000000</TOP_UP_KETTLE>
 <HOP_UTILIZATION>100.0000000</HOP_UTILIZATION>
 <COOLING_LOSS_PCT>4.0000000</COOLING_LOSS_PCT>
 <NOTES>Standard 5 gal/19 liter mead setup for no-boil mead.  Typically the primary fermenter is a 7.5 gal/28 l or larger plastic bucket for easy of access.  Meads are usually aged in glass carboys or kegs to avoid oxygen contamination during long aging periods.</NOTES>
 <DISPLAY_BOIL_SIZE>21.61 L</DISPLAY_BOIL_SIZE>
 <DISPLAY_BATCH_SIZE>18.93 L</DISPLAY_BATCH_SIZE>
 <DISPLAY_TUN_VOLUME>18.93 L</DISPLAY_TUN_VOLUME>
 <DISPLAY_TUN_WEIGHT>4.54 kg</DISPLAY_TUN_WEIGHT>
 <DISPLAY_TOP_UP_WATER>0.00 L</DISPLAY_TOP_UP_WATER>
 <DISPLAY_TRUB_CHILLER_LOSS>0.00 L</DISPLAY_TRUB_CHILLER_LOSS>
 <DISPLAY_LAUTER_DEADSPACE>0.00 L</DISPLAY_LAUTER_DEADSPACE>
 <DISPLAY_TOP_UP_KETTLE>0.00 L</DISPLAY_TOP_UP_KETTLE>
</EQUIPMENT>
<EQUIPMENT>
 <NAME>Pot ( 2 Gal/7.6 L) - Extract</NAME>
 <VERSION>1</VERSION>
 <BOIL_SIZE>6.4352000</BOIL_SIZE>
 <BATCH_SIZE>18.9270589</BATCH_SIZE>
 <TUN_VOLUME>7.5708236</TUN_VOLUME>
 <TUN_WEIGHT>1.1339800</TUN_WEIGHT>
 <TUN_SPECIFIC_HEAT>0.1200000</TUN_SPECIFIC_HEAT>
 <TOP_UP_WATER>14.1952942</TOP_UP_WATER>
 <TRUB_CHILLER_LOSS>0.9463529</TRUB_CHILLER_LOSS>
 <EVAP_RATE>8.2352941</EVAP_RATE>
 <BOIL_TIME>60.0000000</BOIL_TIME>
 <CALC_BOIL_VOLUME>TRUE</CALC_BOIL_VOLUME>
 <LAUTER_DEADSPACE>0.0000000</LAUTER_DEADSPACE>
 <TOP_UP_KETTLE>0.0000000</TOP_UP_KETTLE>
 <HOP_UTILIZATION>100.0000000</HOP_UTILIZATION>
 <COOLING_LOSS_PCT>4.0000000</COOLING_LOSS_PCT>
 <NOTES>Simple brew pot with 2 gallon capacity for extract brewing.  May also be used for partial mash with temperature or infusion mashing.</NOTES>
 <DISPLAY_BOIL_SIZE>6.44 L</DISPLAY_BOIL_SIZE>
 <DISPLAY_BATCH_SIZE>18.93 L</DISPLAY_BATCH_SIZE>
 <DISPLAY_TUN_VOLUME>7.57 L</DISPLAY_TUN_VOLUME>
 <DISPLAY_TUN_WEIGHT>1.13 kg</DISPLAY_TUN_WEIGHT>
 <DISPLAY_TOP_UP_WATER>14.20 L</DISPLAY_TOP_UP_WATER>
 <DISPLAY_TRUB_CHILLER_LOSS>0.95 L</DISPLAY_TRUB_CHILLER_LOSS>
 <DISPLAY_LAUTER_DEADSPACE>0.00 L</DISPLAY_LAUTER_DEADSPACE>
 <DISPLAY_TOP_UP_KETTLE>0.00 L</DISPLAY_TOP_UP_KETTLE>
</EQUIPMENT>
<EQUIPMENT>
 <NAME>Pot ( 3 Gal/11.4 L) - Extract</NAME>
 <VERSION>1</VERSION>
 <BOIL_SIZE>10.6748612</BOIL_SIZE>
 <BATCH_SIZE>18.9270589</BATCH_SIZE>
 <TUN_VOLUME>11.3562354</TUN_VOLUME>
 <TUN_WEIGHT>1.3607760</TUN_WEIGHT>
 <TUN_SPECIFIC_HEAT>0.1200000</TUN_SPECIFIC_HEAT>
 <TOP_UP_WATER>11.3562354</TOP_UP_WATER>
 <TRUB_CHILLER_LOSS>1.8927059</TRUB_CHILLER_LOSS>
 <EVAP_RATE>7.8014184</EVAP_RATE>
 <BOIL_TIME>60.0000000</BOIL_TIME>
 <CALC_BOIL_VOLUME>TRUE</CALC_BOIL_VOLUME>
 <LAUTER_DEADSPACE>0.0000000</LAUTER_DEADSPACE>
 <TOP_UP_KETTLE>0.0000000</TOP_UP_KETTLE>
 <HOP_UTILIZATION>100.0000000</HOP_UTILIZATION>
 <COOLING_LOSS_PCT>4.0000000</COOLING_LOSS_PCT>
 <NOTES>Simple Brew Pot with a 3 Gallon Capacity - leaving a workable boil volume of around 2.5 gal.  Used for extract or partial mash brewing.</NOTES>
 <DISPLAY_BOIL_SIZE>10.67 L</DISPLAY_BOIL_SIZE>
 <DISPLAY_BATCH_SIZE>18.93 L</DISPLAY_BATCH_SIZE>
 <DISPLAY_TUN_VOLUME>11.36 L</DISPLAY_TUN_VOLUME>
 <DISPLAY_TUN_WEIGHT>1.36 kg</DISPLAY_TUN_WEIGHT>
 <DISPLAY_TOP_UP_WATER>11.36 L</DISPLAY_TOP_UP_WATER>
 <DISPLAY_TRUB_CHILLER_LOSS>1.89 L</DISPLAY_TRUB_CHILLER_LOSS>
 <DISPLAY_LAUTER_DEADSPACE>0.00 L</DISPLAY_LAUTER_DEADSPACE>
 <DISPLAY_TOP_UP_KETTLE>0.00 L</DISPLAY_TOP_UP_KETTLE>
</EQUIPMENT>
<EQUIPMENT>
 <NAME>Pot ( 4 Gal/15.1 L) - Extract</NAME>
 <VERSION>1</VERSION>
 <BOIL_SIZE>13.8924612</BOIL_SIZE>
 <BATCH_SIZE>18.9270589</BATCH_SIZE>
 <TUN_VOLUME>15.1416471</TUN_VOLUME>
 <TUN_WEIGHT>1.8143680</TUN_WEIGHT>
 <TUN_SPECIFIC_HEAT>0.1200000</TUN_SPECIFIC_HEAT>
 <TOP_UP_WATER>8.5171765</TOP_UP_WATER>
 <TRUB_CHILLER_LOSS>1.8927059</TRUB_CHILLER_LOSS>
 <EVAP_RATE>7.9019074</EVAP_RATE>
 <BOIL_TIME>60.0000000</BOIL_TIME>
 <CALC_BOIL_VOLUME>TRUE</CALC_BOIL_VOLUME>
 <LAUTER_DEADSPACE>0.0000000</LAUTER_DEADSPACE>
 <TOP_UP_KETTLE>0.0000000</TOP_UP_KETTLE>
 <HOP_UTILIZATION>100.0000000</HOP_UTILIZATION>
 <COOLING_LOSS_PCT>4.0000000</COOLING_LOSS_PCT>
 <NOTES>Simple Brew Pot with a 4 Gallon Capacity - leaving a workable boil volume of around 3.25 gal.  Used for extract or partial mash brewing.</NOTES>
 <DISPLAY_BOIL_SIZE>13.89 L</DISPLAY_BOIL_SIZE>
 <DISPLAY_BATCH_SIZE>18.93 L</DISPLAY_BATCH_SIZE>
 <DISPLAY_TUN_VOLUME>15.14 L</DISPLAY_TUN_VOLUME>
 <DISPLAY_TUN_WEIGHT>1.81 kg</DISPLAY_TUN_WEIGHT>
 <DISPLAY_TOP_UP_WATER>8.52 L</DISPLAY_TOP_UP_WATER>
 <DISPLAY_TRUB_CHILLER_LOSS>1.89 L</DISPLAY_TRUB_CHILLER_LOSS>
 <DISPLAY_LAUTER_DEADSPACE>0.00 L</DISPLAY_LAUTER_DEADSPACE>
 <DISPLAY_TOP_UP_KETTLE>0.00 L</DISPLAY_TOP_UP_KETTLE>
</EQUIPMENT>
<EQUIPMENT>
 <NAME>Pot ( 5 Gal/19 L) - Mini-BIAB</NAME>
 <VERSION>1</VERSION>
 <BOIL_SIZE>16.2699062</BOIL_SIZE>
 <BATCH_SIZE>10.9999366</BATCH_SIZE>
 <TUN_VOLUME>18.9998905</TUN_VOLUME>
 <TUN_WEIGHT>0.9999992</TUN_WEIGHT>
 <TUN_SPECIFIC_HEAT>0.3000000</TUN_SPECIFIC_HEAT>
 <TOP_UP_WATER>0.0000000</TOP_UP_WATER>
 <TRUB_CHILLER_LOSS>1.9199889</TRUB_CHILLER_LOSS>
 <EVAP_RATE>17.3939766</EVAP_RATE>
 <BOIL_TIME>60.0000000</BOIL_TIME>
 <CALC_BOIL_VOLUME>TRUE</CALC_BOIL_VOLUME>
 <LAUTER_DEADSPACE>0.0000000</LAUTER_DEADSPACE>
 <TOP_UP_KETTLE>0.0000000</TOP_UP_KETTLE>
 <HOP_UTILIZATION>100.0000000</HOP_UTILIZATION>
 <COOLING_LOSS_PCT>4.0000000</COOLING_LOSS_PCT>
 <NOTES>Sample Brew-In-A-Bag equipment profile set up for a 19 litre pot (diameter of 29cm or 15 inches) using a polyester grain bag to hold the grain.  This profile should be used with the BIAB mash profiles available in the BeerSmith mash profiles area. As this is a small pot size, it may be necessary to hold back some mash water until after the bag has been removed to prevent over-flow.  The above assumes loose pellet hops and only clear, chilled wort transferred from the kettle using no trub management techniques. Experienced brewers should adjust &#39;Loss to Trub and Chiller&#39; and &#39;Brewhouse Efficiency&#39; accordingly to suit their trub management techniques.</NOTES>
 <DISPLAY_BOIL_SIZE>16.27 L</DISPLAY_BOIL_SIZE>
 <DISPLAY_BATCH_SIZE>11.00 L</DISPLAY_BATCH_SIZE>
 <DISPLAY_TUN_VOLUME>19.00 L</DISPLAY_TUN_VOLUME>
 <DISPLAY_TUN_WEIGHT>1.00 kg</DISPLAY_TUN_WEIGHT>
 <DISPLAY_TOP_UP_WATER>0.00 L</DISPLAY_TOP_UP_WATER>
 <DISPLAY_TRUB_CHILLER_LOSS>1.92 L</DISPLAY_TRUB_CHILLER_LOSS>
 <DISPLAY_LAUTER_DEADSPACE>0.00 L</DISPLAY_LAUTER_DEADSPACE>
 <DISPLAY_TOP_UP_KETTLE>0.00 L</DISPLAY_TOP_UP_KETTLE>
</EQUIPMENT>
<EQUIPMENT>
 <NAME>Pot (13 Gal/50 L) - BIAB</NAME>
 <VERSION>1</VERSION>
 <BOIL_SIZE>35.9897926</BOIL_SIZE>
 <BATCH_SIZE>23.0198673</BATCH_SIZE>
 <TUN_VOLUME>49.9997118</TUN_VOLUME>
 <TUN_WEIGHT>4.4996363</TUN_WEIGHT>
 <TUN_SPECIFIC_HEAT>0.3000000</TUN_SPECIFIC_HEAT>
 <TOP_UP_WATER>0.0000000</TOP_UP_WATER>
 <TRUB_CHILLER_LOSS>3.8299779</TRUB_CHILLER_LOSS>
 <EVAP_RATE>14.9485968</EVAP_RATE>
 <BOIL_TIME>90.0000000</BOIL_TIME>
 <CALC_BOIL_VOLUME>TRUE</CALC_BOIL_VOLUME>
 <LAUTER_DEADSPACE>0.0000000</LAUTER_DEADSPACE>
 <TOP_UP_KETTLE>0.0000000</TOP_UP_KETTLE>
 <HOP_UTILIZATION>100.0000000</HOP_UTILIZATION>
 <COOLING_LOSS_PCT>4.0000000</COOLING_LOSS_PCT>
 <NOTES>Sample Brew-In-A-Bag equipment profile set up for a 50 litre brew pot (diameter of 40cm or 16 inches) using a polyester grain bag to hold the grain.  This profile should be used with the BIAB mash profiles available in the BeerSmith mash profiles area.  The above assumes loose pellet hops and only clear, chilled wort transferred from the kettle using no trub management techniques. Experienced brewers should adjust &#39;Loss to Trub and Chiller&#39; and &#39;Brewhouse Efficiency&#39; accordingly to suit their trub management techniques.</NOTES>
 <DISPLAY_BOIL_SIZE>35.99 L</DISPLAY_BOIL_SIZE>
 <DISPLAY_BATCH_SIZE>23.02 L</DISPLAY_BATCH_SIZE>
 <DISPLAY_TUN_VOLUME>50.00 L</DISPLAY_TUN_VOLUME>
 <DISPLAY_TUN_WEIGHT>4.50 kg</DISPLAY_TUN_WEIGHT>
 <DISPLAY_TOP_UP_WATER>0.00 L</DISPLAY_TOP_UP_WATER>
 <DISPLAY_TRUB_CHILLER_LOSS>3.83 L</DISPLAY_TRUB_CHILLER_LOSS>
 <DISPLAY_LAUTER_DEADSPACE>0.00 L</DISPLAY_LAUTER_DEADSPACE>
 <DISPLAY_TOP_UP_KETTLE>0.00 L</DISPLAY_TOP_UP_KETTLE>
</EQUIPMENT>
<EQUIPMENT>
 <NAME>Pot (18.5 Gal/70 L) - BIAB</NAME>
 <VERSION>1</VERSION>
 <BOIL_SIZE>56.3196754</BOIL_SIZE>
 <BATCH_SIZE>37.9997810</BATCH_SIZE>
 <TUN_VOLUME>69.9895966</TUN_VOLUME>
 <TUN_WEIGHT>4.4996363</TUN_WEIGHT>
 <TUN_SPECIFIC_HEAT>0.3000000</TUN_SPECIFIC_HEAT>
 <TOP_UP_WATER>0.0000000</TOP_UP_WATER>
 <TRUB_CHILLER_LOSS>6.3399635</TRUB_CHILLER_LOSS>
 <EVAP_RATE>12.0857008</EVAP_RATE>
 <BOIL_TIME>90.0000000</BOIL_TIME>
 <CALC_BOIL_VOLUME>TRUE</CALC_BOIL_VOLUME>
 <LAUTER_DEADSPACE>0.0000000</LAUTER_DEADSPACE>
 <TOP_UP_KETTLE>0.0000000</TOP_UP_KETTLE>
 <HOP_UTILIZATION>100.0000000</HOP_UTILIZATION>
 <COOLING_LOSS_PCT>4.0000000</COOLING_LOSS_PCT>
 <NOTES>Sample Brew-in-a-bag equipment profile set up for a 70 liter brewing pot  (diameter of 45cm or 18 inches) and using a polyester grain bag to hold the grain.  This profile should be used with the BIAB mash profiles available in the BeerSmith mash profiles area. The above assumes loose pellet hops and only clear, chilled wort transferred from the kettle using no trub management techniques. Experienced brewers should adjust &#39;Loss to Trub and Chiller&#39; and &#39;Brewhouse Efficiency&#39; accordingly to suit their trub management techniques. Careful when mashing in as this profile approaches the pot limits.</NOTES>
 <DISPLAY_BOIL_SIZE>56.32 L</DISPLAY_BOIL_SIZE>
 <DISPLAY_BATCH_SIZE>38.00 L</DISPLAY_BATCH_SIZE>
 <DISPLAY_TUN_VOLUME>69.99 L</DISPLAY_TUN_VOLUME>
 <DISPLAY_TUN_WEIGHT>4.50 kg</DISPLAY_TUN_WEIGHT>
 <DISPLAY_TOP_UP_WATER>0.00 L</DISPLAY_TOP_UP_WATER>
 <DISPLAY_TRUB_CHILLER_LOSS>6.34 L</DISPLAY_TRUB_CHILLER_LOSS>
 <DISPLAY_LAUTER_DEADSPACE>0.00 L</DISPLAY_LAUTER_DEADSPACE>
 <DISPLAY_TOP_UP_KETTLE>0.00 L</DISPLAY_TOP_UP_KETTLE>
</EQUIPMENT>
<EQUIPMENT>
 <NAME>Pot (18.5 Gal/70 L) and Cooler (9.5 Gal/40 L)  - All Grain</NAME>
 <VERSION>1</VERSION>
 <BOIL_SIZE>37.0591814</BOIL_SIZE>
 <BATCH_SIZE>23.0153036</BATCH_SIZE>
 <TUN_VOLUME>37.8541178</TUN_VOLUME>
 <TUN_WEIGHT>4.0823280</TUN_WEIGHT>
 <TUN_SPECIFIC_HEAT>0.3000000</TUN_SPECIFIC_HEAT>
 <TOP_UP_WATER>0.0000000</TOP_UP_WATER>
 <TRUB_CHILLER_LOSS>2.8390588</TRUB_CHILLER_LOSS>
 <EVAP_RATE>18.3180116</EVAP_RATE>
 <BOIL_TIME>90.0000000</BOIL_TIME>
 <CALC_BOIL_VOLUME>TRUE</CALC_BOIL_VOLUME>
 <LAUTER_DEADSPACE>3.0283294</LAUTER_DEADSPACE>
 <TOP_UP_KETTLE>0.0000000</TOP_UP_KETTLE>
 <HOP_UTILIZATION>100.0000000</HOP_UTILIZATION>
 <COOLING_LOSS_PCT>4.0000000</COOLING_LOSS_PCT>
 <NOTES>Based on a 18.5 Gal/70 L pot with a diameter of 18 inches/45 cm and a 9.5 Gal/40 L cooler. The above assumes loose pellet hops and only clear, chilled wort transferred from the kettle using no trub management techniques. Experienced brewers should adjust &#39;Loss to Trub and Chiller&#39; and &#39;Brewhouse Efficiency&#39; accordingly to suit their trub management techniques.</NOTES>
 <DISPLAY_BOIL_SIZE>37.06 L</DISPLAY_BOIL_SIZE>
 <DISPLAY_BATCH_SIZE>23.02 L</DISPLAY_BATCH_SIZE>
 <DISPLAY_TUN_VOLUME>37.85 L</DISPLAY_TUN_VOLUME>
 <DISPLAY_TUN_WEIGHT>4.08 kg</DISPLAY_TUN_WEIGHT>
 <DISPLAY_TOP_UP_WATER>0.00 L</DISPLAY_TOP_UP_WATER>
 <DISPLAY_TRUB_CHILLER_LOSS>2.84 L</DISPLAY_TRUB_CHILLER_LOSS>
 <DISPLAY_LAUTER_DEADSPACE>3.03 L</DISPLAY_LAUTER_DEADSPACE>
 <DISPLAY_TOP_UP_KETTLE>0.00 L</DISPLAY_TOP_UP_KETTLE>
</EQUIPMENT>
<EQUIPMENT>
 <NAME>Pot (36L) - Mini-BIAB</NAME>
 <VERSION>1</VERSION>
 <BOIL_SIZE>29.9166276</BOIL_SIZE>
 <BATCH_SIZE>22.9998674</BATCH_SIZE>
 <TUN_VOLUME>35.9997925</TUN_VOLUME>
 <TUN_WEIGHT>1.9999987</TUN_WEIGHT>
 <TUN_SPECIFIC_HEAT>0.2150000</TUN_SPECIFIC_HEAT>
 <TOP_UP_WATER>0.0000000</TOP_UP_WATER>
 <TRUB_CHILLER_LOSS>1.9199889</TRUB_CHILLER_LOSS>
 <EVAP_RATE>13.3704139</EVAP_RATE>
 <BOIL_TIME>60.0000000</BOIL_TIME>
 <CALC_BOIL_VOLUME>TRUE</CALC_BOIL_VOLUME>
 <LAUTER_DEADSPACE>0.0000000</LAUTER_DEADSPACE>
 <TOP_UP_KETTLE>0.0000000</TOP_UP_KETTLE>
 <HOP_UTILIZATION>100.0000000</HOP_UTILIZATION>
 <COOLING_LOSS_PCT>4.0000000</COOLING_LOSS_PCT>
 <NOTES>Sample Brew-In-A-Bag equipment profile set up for a 36 litre pot using a polyester grain bag to hold the grain.  This profile should be used with the BIAB mash profiles available in the BeerSmith mash profiles area. As this is a small pot size, it may be necessary to hold back some mash water until after the bag has been removed to prevent over-flow.  The above assumes loose pellet hops and only clear, chilled wort transferred from the kettle using no trub management techniques. Experienced brewers should adjust &#39;Loss to Trub and Chiller&#39; and &#39;Brewhouse Efficiency&#39; accordingly to suit their trub management techniques.</NOTES>
 <DISPLAY_BOIL_SIZE>29.92 L</DISPLAY_BOIL_SIZE>
 <DISPLAY_BATCH_SIZE>23.00 L</DISPLAY_BATCH_SIZE>
 <DISPLAY_TUN_VOLUME>36.00 L</DISPLAY_TUN_VOLUME>
 <DISPLAY_TUN_WEIGHT>2.00 kg</DISPLAY_TUN_WEIGHT>
 <DISPLAY_TOP_UP_WATER>0.00 L</DISPLAY_TOP_UP_WATER>
 <DISPLAY_TRUB_CHILLER_LOSS>1.92 L</DISPLAY_TRUB_CHILLER_LOSS>
 <DISPLAY_LAUTER_DEADSPACE>0.00 L</DISPLAY_LAUTER_DEADSPACE>
 <DISPLAY_TOP_UP_KETTLE>0.00 L</DISPLAY_TOP_UP_KETTLE>
</EQUIPMENT>
<EQUIPMENT>
 <NAME>Pot and Cooler ( 5 Gal/19 L) - All Grain</NAME>
 <VERSION>1</VERSION>
 <BOIL_SIZE>24.6808848</BOIL_SIZE>
 <BATCH_SIZE>18.9270589</BATCH_SIZE>
 <TUN_VOLUME>18.9270589</TUN_VOLUME>
 <TUN_WEIGHT>1.8143680</TUN_WEIGHT>
 <TUN_SPECIFIC_HEAT>0.3000000</TUN_SPECIFIC_HEAT>
 <TOP_UP_WATER>0.0000000</TOP_UP_WATER>
 <TRUB_CHILLER_LOSS>2.8390588</TRUB_CHILLER_LOSS>
 <EVAP_RATE>8.2822086</EVAP_RATE>
 <BOIL_TIME>60.0000000</BOIL_TIME>
 <CALC_BOIL_VOLUME>TRUE</CALC_BOIL_VOLUME>
 <LAUTER_DEADSPACE>0.9463529</LAUTER_DEADSPACE>
 <TOP_UP_KETTLE>0.0000000</TOP_UP_KETTLE>
 <HOP_UTILIZATION>100.0000000</HOP_UTILIZATION>
 <COOLING_LOSS_PCT>4.0000000</COOLING_LOSS_PCT>
 <NOTES>Popular all grain setup.  5 Gallon cooler as mash tun with false bottom, and 7-9 gallon brewpot capable of boiling at least 6 gallons of wort without spilling over.  Primarily used for single infusion mashes.</NOTES>
 <DISPLAY_BOIL_SIZE>24.68 L</DISPLAY_BOIL_SIZE>
 <DISPLAY_BATCH_SIZE>18.93 L</DISPLAY_BATCH_SIZE>
 <DISPLAY_TUN_VOLUME>18.93 L</DISPLAY_TUN_VOLUME>
 <DISPLAY_TUN_WEIGHT>1.81 kg</DISPLAY_TUN_WEIGHT>
 <DISPLAY_TOP_UP_WATER>0.00 L</DISPLAY_TOP_UP_WATER>
 <DISPLAY_TRUB_CHILLER_LOSS>2.84 L</DISPLAY_TRUB_CHILLER_LOSS>
 <DISPLAY_LAUTER_DEADSPACE>0.95 L</DISPLAY_LAUTER_DEADSPACE>
 <DISPLAY_TOP_UP_KETTLE>0.00 L</DISPLAY_TOP_UP_KETTLE>
</EQUIPMENT>
<EQUIPMENT>
 <NAME>Pot and Cooler ( 5 Gal/19 L) - Extract/Partial Mash</NAME>
 <VERSION>1</VERSION>
 <BOIL_SIZE>16.1637083</BOIL_SIZE>
 <BATCH_SIZE>18.9270589</BATCH_SIZE>
 <TUN_VOLUME>18.9270589</TUN_VOLUME>
 <TUN_WEIGHT>2.2679600</TUN_WEIGHT>
 <TUN_SPECIFIC_HEAT>0.1200000</TUN_SPECIFIC_HEAT>
 <TOP_UP_WATER>7.5708236</TOP_UP_WATER>
 <TRUB_CHILLER_LOSS>2.8390588</TRUB_CHILLER_LOSS>
 <EVAP_RATE>8.6651054</EVAP_RATE>
 <BOIL_TIME>60.0000000</BOIL_TIME>
 <CALC_BOIL_VOLUME>TRUE</CALC_BOIL_VOLUME>
 <LAUTER_DEADSPACE>0.9463529</LAUTER_DEADSPACE>
 <TOP_UP_KETTLE>0.0000000</TOP_UP_KETTLE>
 <HOP_UTILIZATION>100.0000000</HOP_UTILIZATION>
 <COOLING_LOSS_PCT>4.0000000</COOLING_LOSS_PCT>
 <NOTES>Simple Brew Pot with a 5 Gallon Capacity - leaving a workable boil volume of around 4.5 gal.   Used for extract or partial mash brewing.  Note top-up water is still required as we can&#39;t reach a full volume boil in this setup.</NOTES>
 <DISPLAY_BOIL_SIZE>16.16 L</DISPLAY_BOIL_SIZE>
 <DISPLAY_BATCH_SIZE>18.93 L</DISPLAY_BATCH_SIZE>
 <DISPLAY_TUN_VOLUME>18.93 L</DISPLAY_TUN_VOLUME>
 <DISPLAY_TUN_WEIGHT>2.27 kg</DISPLAY_TUN_WEIGHT>
 <DISPLAY_TOP_UP_WATER>7.57 L</DISPLAY_TOP_UP_WATER>
 <DISPLAY_TRUB_CHILLER_LOSS>2.84 L</DISPLAY_TRUB_CHILLER_LOSS>
 <DISPLAY_LAUTER_DEADSPACE>0.95 L</DISPLAY_LAUTER_DEADSPACE>
 <DISPLAY_TOP_UP_KETTLE>0.00 L</DISPLAY_TOP_UP_KETTLE>
</EQUIPMENT>
<EQUIPMENT>
 <NAME>Pot and Cooler (10 Gal/37.8 L) - All Grain</NAME>
 <VERSION>1</VERSION>
 <BOIL_SIZE>47.5826261</BOIL_SIZE>
 <BATCH_SIZE>37.8541178</BATCH_SIZE>
 <TUN_VOLUME>37.8541178</TUN_VOLUME>
 <TUN_WEIGHT>4.0823280</TUN_WEIGHT>
 <TUN_SPECIFIC_HEAT>0.3000000</TUN_SPECIFIC_HEAT>
 <TOP_UP_WATER>0.0000000</TOP_UP_WATER>
 <TRUB_CHILLER_LOSS>3.7854118</TRUB_CHILLER_LOSS>
 <EVAP_RATE>8.9896579</EVAP_RATE>
 <BOIL_TIME>60.0000000</BOIL_TIME>
 <CALC_BOIL_VOLUME>TRUE</CALC_BOIL_VOLUME>
 <LAUTER_DEADSPACE>3.0283294</LAUTER_DEADSPACE>
 <TOP_UP_KETTLE>0.0000000</TOP_UP_KETTLE>
 <HOP_UTILIZATION>100.0000000</HOP_UTILIZATION>
 <COOLING_LOSS_PCT>4.0000000</COOLING_LOSS_PCT>
 <NOTES>Popular 10 gallon setup for all grain brewing.  Uses a 10 gallon water cooler as mash tun for single infusion mashes and a 15 gallon brew pot for full size boil of the 12+ gallons of wort.</NOTES>
 <DISPLAY_BOIL_SIZE>47.58 L</DISPLAY_BOIL_SIZE>
 <DISPLAY_BATCH_SIZE>37.85 L</DISPLAY_BATCH_SIZE>
 <DISPLAY_TUN_VOLUME>37.85 L</DISPLAY_TUN_VOLUME>
 <DISPLAY_TUN_WEIGHT>4.08 kg</DISPLAY_TUN_WEIGHT>
 <DISPLAY_TOP_UP_WATER>0.00 L</DISPLAY_TOP_UP_WATER>
 <DISPLAY_TRUB_CHILLER_LOSS>3.79 L</DISPLAY_TRUB_CHILLER_LOSS>
 <DISPLAY_LAUTER_DEADSPACE>3.03 L</DISPLAY_LAUTER_DEADSPACE>
 <DISPLAY_TOP_UP_KETTLE>0.00 L</DISPLAY_TOP_UP_KETTLE>
</EQUIPMENT>
<EQUIPMENT>
 <NAME>Stainless Kegs (10 Gal/37.8 L) - All Grain</NAME>
 <VERSION>1</VERSION>
 <BOIL_SIZE>50.8759344</BOIL_SIZE>
 <BATCH_SIZE>37.8541178</BATCH_SIZE>
 <TUN_VOLUME>56.7811768</TUN_VOLUME>
 <TUN_WEIGHT>9.0718400</TUN_WEIGHT>
 <TUN_SPECIFIC_HEAT>0.1500000</TUN_SPECIFIC_HEAT>
 <TOP_UP_WATER>0.0000000</TOP_UP_WATER>
 <TRUB_CHILLER_LOSS>3.7854118</TRUB_CHILLER_LOSS>
 <EVAP_RATE>14.8809524</EVAP_RATE>
 <BOIL_TIME>60.0000000</BOIL_TIME>
 <CALC_BOIL_VOLUME>TRUE</CALC_BOIL_VOLUME>
 <LAUTER_DEADSPACE>3.7854118</LAUTER_DEADSPACE>
 <TOP_UP_KETTLE>0.0000000</TOP_UP_KETTLE>
 <HOP_UTILIZATION>100.0000000</HOP_UTILIZATION>
 <COOLING_LOSS_PCT>4.0000000</COOLING_LOSS_PCT>
 <NOTES>Popular 10 gallon batch setup for all grain brewing.  Uses two large stainless 15 gal/58 l kegs for the boil pot and mash tun with the tops cut off the keg.  A third keg is often used as a pot to heat mash tun water.</NOTES>
 <DISPLAY_BOIL_SIZE>50.88 L</DISPLAY_BOIL_SIZE>
 <DISPLAY_BATCH_SIZE>37.85 L</DISPLAY_BATCH_SIZE>
 <DISPLAY_TUN_VOLUME>56.78 L</DISPLAY_TUN_VOLUME>
 <DISPLAY_TUN_WEIGHT>9.07 kg</DISPLAY_TUN_WEIGHT>
 <DISPLAY_TOP_UP_WATER>0.00 L</DISPLAY_TOP_UP_WATER>
 <DISPLAY_TRUB_CHILLER_LOSS>3.79 L</DISPLAY_TRUB_CHILLER_LOSS>
 <DISPLAY_LAUTER_DEADSPACE>3.79 L</DISPLAY_LAUTER_DEADSPACE>
 <DISPLAY_TOP_UP_KETTLE>0.00 L</DISPLAY_TOP_UP_KETTLE>
</EQUIPMENT>
</EQUIPMENTS>
